{
"meta":{"test_sets":[],"test_metrics":[],"learn_metrics":[{"best_value":"Min","name":"RMSE"}],"launch_mode":"Train","parameters":"","iteration_count":1000,"learn_sets":["learn"],"name":"experiment"},
"iterations":[
{"learn":[14.59871775],"iteration":0,"passed_time":0.1417535825,"remaining_time":141.6118289},
{"learn":[14.22518863],"iteration":1,"passed_time":0.1442229747,"remaining_time":71.96726437},
{"learn":[13.8866124],"iteration":2,"passed_time":0.1523107247,"remaining_time":50.61793085},
{"learn":[13.52356875],"iteration":3,"passed_time":0.155552135,"remaining_time":38.73248162},
{"learn":[13.18870211],"iteration":4,"passed_time":0.165176563,"remaining_time":32.87013604},
{"learn":[12.9124226],"iteration":5,"passed_time":0.16756293,"remaining_time":27.75959206},
{"learn":[12.60003351],"iteration":6,"passed_time":0.1699849248,"remaining_time":24.11357575},
{"learn":[12.32990573],"iteration":7,"passed_time":0.1741179921,"remaining_time":21.59063102},
{"learn":[12.0660619],"iteration":8,"passed_time":0.1770475201,"remaining_time":19.49489915},
{"learn":[11.77309809],"iteration":9,"passed_time":0.1794025974,"remaining_time":17.76085715},
{"learn":[11.49227636],"iteration":10,"passed_time":0.1816780142,"remaining_time":16.3345051},
{"learn":[11.26264833],"iteration":11,"passed_time":0.1838434675,"remaining_time":15.13644549},
{"learn":[11.04260393],"iteration":12,"passed_time":0.1860353622,"remaining_time":14.12437712},
{"learn":[10.79916926],"iteration":13,"passed_time":0.1886523485,"remaining_time":13.2865154},
{"learn":[10.5541002],"iteration":14,"passed_time":0.19069411,"remaining_time":12.52224656},
{"learn":[10.31918115],"iteration":15,"passed_time":0.1925916188,"remaining_time":11.84438455},
{"learn":[10.10004441],"iteration":16,"passed_time":0.1943499264,"remaining_time":11.23799869},
{"learn":[9.894556723],"iteration":17,"passed_time":0.1962730068,"remaining_time":10.70778293},
{"learn":[9.690174082],"iteration":18,"passed_time":0.1982439569,"remaining_time":10.23564851},
{"learn":[9.506034866],"iteration":19,"passed_time":0.2003399834,"remaining_time":9.816659185},
{"learn":[9.338524633],"iteration":20,"passed_time":0.202681907,"remaining_time":9.448837472},
{"learn":[9.170203312],"iteration":21,"passed_time":0.2053264128,"remaining_time":9.127692352},
{"learn":[9.010299969],"iteration":22,"passed_time":0.207698678,"remaining_time":8.822678628},
{"learn":[8.843866678],"iteration":23,"passed_time":0.2106661297,"remaining_time":8.567089274},
{"learn":[8.690548059],"iteration":24,"passed_time":0.2151252836,"remaining_time":8.389886061},
{"learn":[8.555307687],"iteration":25,"passed_time":0.2175118779,"remaining_time":8.148329579},
{"learn":[8.413851302],"iteration":26,"passed_time":0.2205185999,"remaining_time":7.946836954},
{"learn":[8.29256019],"iteration":27,"passed_time":0.2235263427,"remaining_time":7.759557324},
{"learn":[8.162193833],"iteration":28,"passed_time":0.2258089925,"remaining_time":7.56070799},
{"learn":[8.040736294],"iteration":29,"passed_time":0.2313049176,"remaining_time":7.478859003},
{"learn":[7.921220278],"iteration":30,"passed_time":0.2332198458,"remaining_time":7.290000985},
{"learn":[7.809589039],"iteration":31,"passed_time":0.2351155352,"remaining_time":7.112244938},
{"learn":[7.699675801],"iteration":32,"passed_time":0.237182693,"remaining_time":6.95017164},
{"learn":[7.60645267],"iteration":33,"passed_time":0.2389246866,"remaining_time":6.788271977},
{"learn":[7.498880302],"iteration":34,"passed_time":0.2409713542,"remaining_time":6.643924481},
{"learn":[7.401158744],"iteration":35,"passed_time":0.2430291704,"remaining_time":6.507781118},
{"learn":[7.306431077],"iteration":36,"passed_time":0.2450101017,"remaining_time":6.376884538},
{"learn":[7.223863468],"iteration":37,"passed_time":0.2468432092,"remaining_time":6.249030718},
{"learn":[7.143477682],"iteration":38,"passed_time":0.2491258461,"remaining_time":6.13871636},
{"learn":[7.062817131],"iteration":39,"passed_time":0.251650468,"remaining_time":6.039611233},
{"learn":[6.990793435],"iteration":40,"passed_time":0.2535300691,"remaining_time":5.930130153},
{"learn":[6.931862224],"iteration":41,"passed_time":0.255789026,"remaining_time":5.834425878},
{"learn":[6.858296558],"iteration":42,"passed_time":0.257841332,"remaining_time":5.738468714},
{"learn":[6.786268161],"iteration":43,"passed_time":0.2598200723,"remaining_time":5.645181571},
{"learn":[6.717118549],"iteration":44,"passed_time":0.2616649448,"remaining_time":5.553111607},
{"learn":[6.652948106],"iteration":45,"passed_time":0.2633754954,"remaining_time":5.462178752},
{"learn":[6.589686076],"iteration":46,"passed_time":0.2652993427,"remaining_time":5.379367523},
{"learn":[6.531283097],"iteration":47,"passed_time":0.2669880518,"remaining_time":5.295263026},
{"learn":[6.471368031],"iteration":48,"passed_time":0.2687706437,"remaining_time":5.216344533},
{"learn":[6.416481395],"iteration":49,"passed_time":0.2707222264,"remaining_time":5.143722302},
{"learn":[6.369870822],"iteration":50,"passed_time":0.2728638428,"remaining_time":5.077407585},
{"learn":[6.325678067],"iteration":51,"passed_time":0.2747879691,"remaining_time":5.009596053},
{"learn":[6.275766122],"iteration":52,"passed_time":0.2767836191,"remaining_time":4.945548816},
{"learn":[6.224773967],"iteration":53,"passed_time":0.2783821953,"remaining_time":4.876843644},
{"learn":[6.182249254],"iteration":54,"passed_time":0.2800165671,"remaining_time":4.811193744},
{"learn":[6.139904173],"iteration":55,"passed_time":0.281694657,"remaining_time":4.748567075},
{"learn":[6.100525536],"iteration":56,"passed_time":0.2833798004,"remaining_time":4.688195645},
{"learn":[6.062568564],"iteration":57,"passed_time":0.2851094328,"remaining_time":4.630570442},
{"learn":[6.030559288],"iteration":58,"passed_time":0.2871906173,"remaining_time":4.580446964},
{"learn":[5.997931376],"iteration":59,"passed_time":0.2892232353,"remaining_time":4.53116402},
{"learn":[5.964103835],"iteration":60,"passed_time":0.291130108,"remaining_time":4.481494613},
{"learn":[5.933729724],"iteration":61,"passed_time":0.2932759371,"remaining_time":4.436981113},
{"learn":[5.901932711],"iteration":62,"passed_time":0.2952816724,"remaining_time":4.391729},
{"learn":[5.873727795],"iteration":63,"passed_time":0.2970409854,"remaining_time":4.344224411},
{"learn":[5.846485734],"iteration":64,"passed_time":0.2990353456,"remaining_time":4.301508433},
{"learn":[5.820630862],"iteration":65,"passed_time":0.3008662324,"remaining_time":4.257713046},
{"learn":[5.793646238],"iteration":66,"passed_time":0.3034894288,"remaining_time":4.226203538},
{"learn":[5.765388646],"iteration":67,"passed_time":0.3056352893,"remaining_time":4.189001318},
{"learn":[5.747073912],"iteration":68,"passed_time":0.307300163,"remaining_time":4.146325388},
{"learn":[5.722315217],"iteration":69,"passed_time":0.309109141,"remaining_time":4.10673573},
{"learn":[5.699970599],"iteration":70,"passed_time":0.3110068575,"remaining_time":4.069371418},
{"learn":[5.682732647],"iteration":71,"passed_time":0.3128283521,"remaining_time":4.032009871},
{"learn":[5.663525791],"iteration":72,"passed_time":0.3145916437,"remaining_time":3.994882927},
{"learn":[5.642381613],"iteration":73,"passed_time":0.3167010773,"remaining_time":3.96304321},
{"learn":[5.621404779],"iteration":74,"passed_time":0.3194669818,"remaining_time":3.940092775},
{"learn":[5.602460129],"iteration":75,"passed_time":0.3215329881,"remaining_time":3.909164223},
{"learn":[5.587337574],"iteration":76,"passed_time":0.3234288589,"remaining_time":3.876945932},
{"learn":[5.572393026],"iteration":77,"passed_time":0.3252011351,"remaining_time":3.844044187},
{"learn":[5.558425806],"iteration":78,"passed_time":0.3271093334,"remaining_time":3.81351514},
{"learn":[5.541518902],"iteration":79,"passed_time":0.329158729,"remaining_time":3.785325384},
{"learn":[5.526157283],"iteration":80,"passed_time":0.3313807802,"remaining_time":3.759739963},
{"learn":[5.511746977],"iteration":81,"passed_time":0.3335265929,"remaining_time":3.733870881},
{"learn":[5.504975022],"iteration":82,"passed_time":0.3345182552,"remaining_time":3.695822169},
{"learn":[5.493980522],"iteration":83,"passed_time":0.3366696526,"remaining_time":3.671302403},
{"learn":[5.480745463],"iteration":84,"passed_time":0.3388100731,"remaining_time":3.647190787},
{"learn":[5.464052013],"iteration":85,"passed_time":0.34151963,"remaining_time":3.629638858},
{"learn":[5.449143727],"iteration":86,"passed_time":0.3432405172,"remaining_time":3.602052784},
{"learn":[5.438255432],"iteration":87,"passed_time":0.3454554004,"remaining_time":3.58017415},
{"learn":[5.425927931],"iteration":88,"passed_time":0.3475866288,"remaining_time":3.55788111},
{"learn":[5.412331217],"iteration":89,"passed_time":0.3495837372,"remaining_time":3.534680009},
{"learn":[5.400691499],"iteration":90,"passed_time":0.3514026757,"remaining_time":3.510165189},
{"learn":[5.391618744],"iteration":91,"passed_time":0.3530002102,"remaining_time":3.483958597},
{"learn":[5.380766572],"iteration":92,"passed_time":0.3548262447,"remaining_time":3.46050972},
{"learn":[5.372207183],"iteration":93,"passed_time":0.3566196724,"remaining_time":3.43720663},
{"learn":[5.362918837],"iteration":94,"passed_time":0.3583175606,"remaining_time":3.413446235},
{"learn":[5.348292324],"iteration":95,"passed_time":0.3605601401,"remaining_time":3.395274653},
{"learn":[5.339772295],"iteration":96,"passed_time":0.3629499353,"remaining_time":3.378801975},
{"learn":[5.331515983],"iteration":97,"passed_time":0.3651896642,"remaining_time":3.36123548},
{"learn":[5.323861644],"iteration":98,"passed_time":0.3670729969,"remaining_time":3.340735053},
{"learn":[5.313277281],"iteration":99,"passed_time":0.3690704061,"remaining_time":3.321633655},
{"learn":[5.30685627],"iteration":100,"passed_time":0.3707737734,"remaining_time":3.300253686},
{"learn":[5.29652059],"iteration":101,"passed_time":0.3726060761,"remaining_time":3.28039467},
{"learn":[5.288350766],"iteration":102,"passed_time":0.3753880372,"remaining_time":3.269156013},
{"learn":[5.27993346],"iteration":103,"passed_time":0.3777193788,"remaining_time":3.254197725},
{"learn":[5.271789139],"iteration":104,"passed_time":0.3797828876,"remaining_time":3.237196994},
{"learn":[5.262684686],"iteration":105,"passed_time":0.3817007326,"remaining_time":3.219249575},
{"learn":[5.251619772],"iteration":106,"passed_time":0.3835024132,"remaining_time":3.20063229},
{"learn":[5.241012171],"iteration":107,"passed_time":0.3852790304,"remaining_time":3.1821194},
{"learn":[5.232684032],"iteration":108,"passed_time":0.3870828496,"remaining_time":3.164135954},
{"learn":[5.224267141],"iteration":109,"passed_time":0.38891917,"remaining_time":3.146709648},
{"learn":[5.216324968],"iteration":110,"passed_time":0.3908307575,"remaining_time":3.130167058},
{"learn":[5.211102527],"iteration":111,"passed_time":0.3929866907,"remaining_time":3.115823048},
{"learn":[5.206364257],"iteration":112,"passed_time":0.3948455613,"remaining_time":3.099362945},
{"learn":[5.196937641],"iteration":113,"passed_time":0.3965670819,"remaining_time":3.082091531},
{"learn":[5.190746047],"iteration":114,"passed_time":0.3985104259,"remaining_time":3.066797625},
{"learn":[5.181885213],"iteration":115,"passed_time":0.4003985719,"remaining_time":3.051313255},
{"learn":[5.178293568],"iteration":116,"passed_time":0.4019755306,"remaining_time":3.033712765},
{"learn":[5.170991438],"iteration":117,"passed_time":0.4041040238,"remaining_time":3.020506347},
{"learn":[5.166257212],"iteration":118,"passed_time":0.4067505805,"remaining_time":3.011321525},
{"learn":[5.161421246],"iteration":119,"passed_time":0.4089504091,"remaining_time":2.998969666},
{"learn":[5.158223542],"iteration":120,"passed_time":0.4109679387,"remaining_time":2.985461307},
{"learn":[5.15470988],"iteration":121,"passed_time":0.4125571021,"remaining_time":2.969058489},
{"learn":[5.146388143],"iteration":122,"passed_time":0.4143130037,"remaining_time":2.954085401},
{"learn":[5.139529364],"iteration":123,"passed_time":0.4161856906,"remaining_time":2.940150524},
{"learn":[5.134276023],"iteration":124,"passed_time":0.4179060727,"remaining_time":2.925342509},
{"learn":[5.128536065],"iteration":125,"passed_time":0.419909473,"remaining_time":2.912705392},
{"learn":[5.123300353],"iteration":126,"passed_time":0.4217594118,"remaining_time":2.899180838},
{"learn":[5.116200518],"iteration":127,"passed_time":0.4240543011,"remaining_time":2.888869926},
{"learn":[5.108728704],"iteration":128,"passed_time":0.4258375463,"remaining_time":2.875228704},
{"learn":[5.104075866],"iteration":129,"passed_time":0.4278406424,"remaining_time":2.863241222},
{"learn":[5.100317606],"iteration":130,"passed_time":0.4298420309,"remaining_time":2.851394846},
{"learn":[5.095814182],"iteration":131,"passed_time":0.4316920807,"remaining_time":2.83870247},
{"learn":[5.092146915],"iteration":132,"passed_time":0.4334526122,"remaining_time":2.825589585},
{"learn":[5.085258329],"iteration":133,"passed_time":0.4356830548,"remaining_time":2.815683026},
{"learn":[5.079219421],"iteration":134,"passed_time":0.43779848,"remaining_time":2.805153224},
{"learn":[5.076476829],"iteration":135,"passed_time":0.439759915,"remaining_time":2.793768872},
{"learn":[5.072133867],"iteration":136,"passed_time":0.4416474001,"remaining_time":2.78205625},
{"learn":[5.067031564],"iteration":137,"passed_time":0.4435735279,"remaining_time":2.770727399},
{"learn":[5.061358312],"iteration":138,"passed_time":0.4463639543,"remaining_time":2.764887516},
{"learn":[5.056759124],"iteration":139,"passed_time":0.4484226954,"remaining_time":2.754596558},
{"learn":[5.050254],"iteration":140,"passed_time":0.4508750606,"remaining_time":2.746820404},
{"learn":[5.048376474],"iteration":141,"passed_time":0.4523376696,"remaining_time":2.733138877},
{"learn":[5.042603751],"iteration":142,"passed_time":0.4542319675,"remaining_time":2.722215357},
{"learn":[5.037477349],"iteration":143,"passed_time":0.4564962458,"remaining_time":2.713616572},
{"learn":[5.03230489],"iteration":144,"passed_time":0.4585590094,"remaining_time":2.703916918},
{"learn":[5.025976187],"iteration":145,"passed_time":0.460506955,"remaining_time":2.693650271},
{"learn":[5.01952451],"iteration":146,"passed_time":0.462437748,"remaining_time":2.683397272},
{"learn":[5.017569424],"iteration":147,"passed_time":0.4644968159,"remaining_time":2.673995184},
{"learn":[5.008962367],"iteration":148,"passed_time":0.4667604547,"remaining_time":2.665860047},
{"learn":[5.003880266],"iteration":149,"passed_time":0.4690820428,"remaining_time":2.658131576},
{"learn":[4.996387564],"iteration":150,"passed_time":0.4712384945,"remaining_time":2.649546238},
{"learn":[4.993361683],"iteration":151,"passed_time":0.473457796,"remaining_time":2.641396125},
{"learn":[4.99005752],"iteration":152,"passed_time":0.4754487318,"remaining_time":2.632059319},
{"learn":[4.986908764],"iteration":153,"passed_time":0.4783767857,"remaining_time":2.627965978},
{"learn":[4.985207175],"iteration":154,"passed_time":0.480821739,"remaining_time":2.621253997},
{"learn":[4.979003494],"iteration":155,"passed_time":0.4831941703,"remaining_time":2.614204357},
{"learn":[4.973142217],"iteration":156,"passed_time":0.4854883371,"remaining_time":2.606794065},
{"learn":[4.967056696],"iteration":157,"passed_time":0.4878177326,"remaining_time":2.599636271},
{"learn":[4.961460696],"iteration":158,"passed_time":0.4899732043,"remaining_time":2.591619275},
{"learn":[4.954240363],"iteration":159,"passed_time":0.4919120623,"remaining_time":2.582538327},
{"learn":[4.952320707],"iteration":160,"passed_time":0.4932073038,"remaining_time":2.570192099},
{"learn":[4.948337777],"iteration":161,"passed_time":0.496587937,"remaining_time":2.568769699},
{"learn":[4.943228639],"iteration":162,"passed_time":0.4989843521,"remaining_time":2.562269342},
{"learn":[4.938545759],"iteration":163,"passed_time":0.5013924829,"remaining_time":2.555878754},
{"learn":[4.935330572],"iteration":164,"passed_time":0.5035213538,"remaining_time":2.548123215},
{"learn":[4.932051543],"iteration":165,"passed_time":0.5052707315,"remaining_time":2.538528856},
{"learn":[4.928964153],"iteration":166,"passed_time":0.5072736436,"remaining_time":2.530293084},
{"learn":[4.922860227],"iteration":167,"passed_time":0.5092033971,"remaining_time":2.521769205},
{"learn":[4.917668772],"iteration":168,"passed_time":0.5115937614,"remaining_time":2.515588259},
{"learn":[4.910365386],"iteration":169,"passed_time":0.5138881911,"remaining_time":2.508983521},
{"learn":[4.906457206],"iteration":170,"passed_time":0.5167778356,"remaining_time":2.50531477},
{"learn":[4.901996508],"iteration":171,"passed_time":0.5191324193,"remaining_time":2.499079321},
{"learn":[4.896816173],"iteration":172,"passed_time":0.5211100616,"remaining_time":2.491086826},
{"learn":[4.891123132],"iteration":173,"passed_time":0.5230015145,"remaining_time":2.482754316},
{"learn":[4.887630202],"iteration":174,"passed_time":0.5255798026,"remaining_time":2.477733355},
{"learn":[4.885259712],"iteration":175,"passed_time":0.5278685993,"remaining_time":2.471384806},
{"learn":[4.880659728],"iteration":176,"passed_time":0.529993336,"remaining_time":2.464319297},
{"learn":[4.877299723],"iteration":177,"passed_time":0.5320626029,"remaining_time":2.457053144},
{"learn":[4.874038772],"iteration":178,"passed_time":0.5340565884,"remaining_time":2.449499771},
{"learn":[4.86943698],"iteration":179,"passed_time":0.5359947736,"remaining_time":2.441753969},
{"learn":[4.861268711],"iteration":180,"passed_time":0.5379584738,"remaining_time":2.43418779},
{"learn":[4.858673056],"iteration":181,"passed_time":0.5405466795,"remaining_time":2.429490021},
{"learn":[4.854036207],"iteration":182,"passed_time":0.5429627034,"remaining_time":2.424046605},
{"learn":[4.85130244],"iteration":183,"passed_time":0.5453756451,"remaining_time":2.418622426},
{"learn":[4.847510084],"iteration":184,"passed_time":0.5476812454,"remaining_time":2.412757919},
{"learn":[4.845691673],"iteration":185,"passed_time":0.5495455898,"remaining_time":2.405000592},
{"learn":[4.842058646],"iteration":186,"passed_time":0.5514063857,"remaining_time":2.397290864},
{"learn":[4.838623675],"iteration":187,"passed_time":0.5532728782,"remaining_time":2.389667963},
{"learn":[4.834602161],"iteration":188,"passed_time":0.5559129172,"remaining_time":2.385425269},
{"learn":[4.830858976],"iteration":189,"passed_time":0.5588720612,"remaining_time":2.38255984},
{"learn":[4.827590511],"iteration":190,"passed_time":0.5612197762,"remaining_time":2.377103659},
{"learn":[4.822246226],"iteration":191,"passed_time":0.5633322063,"remaining_time":2.370689701},
{"learn":[4.816686395],"iteration":192,"passed_time":0.5652251877,"remaining_time":2.363402728},
{"learn":[4.814797121],"iteration":193,"passed_time":0.5670724047,"remaining_time":2.355981228},
{"learn":[4.811639392],"iteration":194,"passed_time":0.5700530974,"remaining_time":2.35329612},
{"learn":[4.804813432],"iteration":195,"passed_time":0.5722348005,"remaining_time":2.347330508},
{"learn":[4.80251613],"iteration":196,"passed_time":0.5747178914,"remaining_time":2.342631811},
{"learn":[4.800087884],"iteration":197,"passed_time":0.5767759154,"remaining_time":2.336233758},
{"learn":[4.794773135],"iteration":198,"passed_time":0.5788333086,"remaining_time":2.329876785},
{"learn":[4.791664833],"iteration":199,"passed_time":0.5805940109,"remaining_time":2.322376043},
{"learn":[4.785989873],"iteration":200,"passed_time":0.5825604363,"remaining_time":2.315750192},
{"learn":[4.782387142],"iteration":201,"passed_time":0.5859829609,"remaining_time":2.314922786},
{"learn":[4.778623704],"iteration":202,"passed_time":0.5881282865,"remaining_time":2.309055391},
{"learn":[4.775772178],"iteration":203,"passed_time":0.5902576832,"remaining_time":2.303162333},
{"learn":[4.77023101],"iteration":204,"passed_time":0.5922874218,"remaining_time":2.296919514},
{"learn":[4.764496689],"iteration":205,"passed_time":0.5940816401,"remaining_time":2.289809817},
{"learn":[4.763138716],"iteration":206,"passed_time":0.5962931395,"remaining_time":2.284350046},
{"learn":[4.758053283],"iteration":207,"passed_time":0.5994628517,"remaining_time":2.282570089},
{"learn":[4.755063788],"iteration":208,"passed_time":0.6024956375,"remaining_time":2.280258609},
{"learn":[4.752465267],"iteration":209,"passed_time":0.6046277782,"remaining_time":2.274552118},
{"learn":[4.748067377],"iteration":210,"passed_time":0.6068536564,"remaining_time":2.269230023},
{"learn":[4.744163298],"iteration":211,"passed_time":0.6088995323,"remaining_time":2.263268073},
{"learn":[4.736670896],"iteration":212,"passed_time":0.6108669305,"remaining_time":2.257052931},
{"learn":[4.73349255],"iteration":213,"passed_time":0.6129035807,"remaining_time":2.251131843},
{"learn":[4.731864595],"iteration":214,"passed_time":0.615776159,"remaining_time":2.248298999},
{"learn":[4.728398311],"iteration":215,"passed_time":0.6181354323,"remaining_time":2.24360268},
{"learn":[4.723865975],"iteration":216,"passed_time":0.6212806647,"remaining_time":2.241763873},
{"learn":[4.723483365],"iteration":217,"passed_time":0.623328689,"remaining_time":2.235977224},
{"learn":[4.72095416],"iteration":218,"passed_time":0.6252444878,"remaining_time":2.229753173},
{"learn":[4.716173382],"iteration":219,"passed_time":0.6271968804,"remaining_time":2.22369803},
{"learn":[4.710563974],"iteration":220,"passed_time":0.6301435491,"remaining_time":2.221184727},
{"learn":[4.707160263],"iteration":221,"passed_time":0.6327397173,"remaining_time":2.217439189},
{"learn":[4.70408351],"iteration":222,"passed_time":0.6347254576,"remaining_time":2.211577043},
{"learn":[4.702501831],"iteration":223,"passed_time":0.6367659868,"remaining_time":2.205939311},
{"learn":[4.700269738],"iteration":224,"passed_time":0.6384731362,"remaining_time":2.199185247},
{"learn":[4.695346302],"iteration":225,"passed_time":0.6403911191,"remaining_time":2.193197903},
{"learn":[4.689769299],"iteration":226,"passed_time":0.6421990622,"remaining_time":2.186871696},
{"learn":[4.687919514],"iteration":227,"passed_time":0.6450538867,"remaining_time":2.184129827},
{"learn":[4.682982074],"iteration":228,"passed_time":0.6474695478,"remaining_time":2.17990839},
{"learn":[4.679578702],"iteration":229,"passed_time":0.6495712746,"remaining_time":2.174651658},
{"learn":[4.675751423],"iteration":230,"passed_time":0.6515808517,"remaining_time":2.169115476},
{"learn":[4.672710726],"iteration":231,"passed_time":0.6534021113,"remaining_time":2.1629863},
{"learn":[4.6690533],"iteration":232,"passed_time":0.6551657083,"remaining_time":2.156704284},
{"learn":[4.667595702],"iteration":233,"passed_time":0.657111872,"remaining_time":2.151058521},
{"learn":[4.664241291],"iteration":234,"passed_time":0.6590003793,"remaining_time":2.145256554},
{"learn":[4.662246999],"iteration":235,"passed_time":0.6627197067,"remaining_time":2.145414644},
{"learn":[4.658668443],"iteration":236,"passed_time":0.6648686377,"remaining_time":2.140484264},
{"learn":[4.658017572],"iteration":237,"passed_time":0.6668934073,"remaining_time":2.135179732},
{"learn":[4.657656705],"iteration":238,"passed_time":0.6689819416,"remaining_time":2.13010568},
{"learn":[4.653242871],"iteration":239,"passed_time":0.670753157,"remaining_time":2.124051664},
{"learn":[4.6507302],"iteration":240,"passed_time":0.672716396,"remaining_time":2.118637944},
{"learn":[4.647671336],"iteration":241,"passed_time":0.675045436,"remaining_time":2.114398514},
{"learn":[4.645506007],"iteration":242,"passed_time":0.677630442,"remaining_time":2.1109722},
{"learn":[4.641297906],"iteration":243,"passed_time":0.6798623557,"remaining_time":2.106458774},
{"learn":[4.63798107],"iteration":244,"passed_time":0.6816684542,"remaining_time":2.100651767},
{"learn":[4.635062318],"iteration":245,"passed_time":0.6839997628,"remaining_time":2.096487078},
{"learn":[4.631606017],"iteration":246,"passed_time":0.6857913735,"remaining_time":2.09069192},
{"learn":[4.630215494],"iteration":247,"passed_time":0.6879129195,"remaining_time":2.085929498},
{"learn":[4.62729814],"iteration":248,"passed_time":0.6909848525,"remaining_time":2.084054716},
{"learn":[4.624691756],"iteration":249,"passed_time":0.693077163,"remaining_time":2.079231489},
{"learn":[4.621840053],"iteration":250,"passed_time":0.6958507104,"remaining_time":2.076462877},
{"learn":[4.619602091],"iteration":251,"passed_time":0.6986664318,"remaining_time":2.073819409},
{"learn":[4.613584029],"iteration":252,"passed_time":0.7006488353,"remaining_time":2.06871415},
{"learn":[4.6119388],"iteration":253,"passed_time":0.7024103871,"remaining_time":2.062984838},
{"learn":[4.60870702],"iteration":254,"passed_time":0.7053684083,"remaining_time":2.060782212},
{"learn":[4.604771557],"iteration":255,"passed_time":0.7090371477,"remaining_time":2.060639211},
{"learn":[4.604231277],"iteration":256,"passed_time":0.711522732,"remaining_time":2.05704821},
{"learn":[4.600750354],"iteration":257,"passed_time":0.7138748874,"remaining_time":2.053082041},
{"learn":[4.596488253],"iteration":258,"passed_time":0.7158068511,"remaining_time":2.047926165},
{"learn":[4.59470784],"iteration":259,"passed_time":0.7178406589,"remaining_time":2.043084952},
{"learn":[4.588818005],"iteration":260,"passed_time":0.7208633411,"remaining_time":2.041065169},
{"learn":[4.585054174],"iteration":261,"passed_time":0.7230233872,"remaining_time":2.036607862},
{"learn":[4.581471435],"iteration":262,"passed_time":0.7252766345,"remaining_time":2.0324292},
{"learn":[4.577555199],"iteration":263,"passed_time":0.7271377255,"remaining_time":2.027171841},
{"learn":[4.57457145],"iteration":264,"passed_time":0.7287392509,"remaining_time":2.021220186},
{"learn":[4.573029224],"iteration":265,"passed_time":0.730499231,"remaining_time":2.015738479},
{"learn":[4.571326203],"iteration":266,"passed_time":0.7325449232,"remaining_time":2.011069021},
{"learn":[4.571019224],"iteration":267,"passed_time":0.7348852796,"remaining_time":2.007223973},
{"learn":[4.565766631],"iteration":268,"passed_time":0.7370705548,"remaining_time":2.002968682},
{"learn":[4.563383471],"iteration":269,"passed_time":0.7390267223,"remaining_time":1.998109286},
{"learn":[4.558165805],"iteration":270,"passed_time":0.740999137,"remaining_time":1.993315022},
{"learn":[4.55629209],"iteration":271,"passed_time":0.7429060762,"remaining_time":1.988366263},
{"learn":[4.549383848],"iteration":272,"passed_time":0.7447858989,"remaining_time":1.983367577},
{"learn":[4.546227503],"iteration":273,"passed_time":0.7467596897,"remaining_time":1.978640638},
{"learn":[4.540620977],"iteration":274,"passed_time":0.7495057834,"remaining_time":1.975969793},
{"learn":[4.532898237],"iteration":275,"passed_time":0.7519908766,"remaining_time":1.972613749},
{"learn":[4.529757367],"iteration":276,"passed_time":0.7541601469,"remaining_time":1.968439661},
{"learn":[4.52579294],"iteration":277,"passed_time":0.7563033492,"remaining_time":1.964212295},
{"learn":[4.521572155],"iteration":278,"passed_time":0.7583749663,"remaining_time":1.959814877},
{"learn":[4.518818099],"iteration":279,"passed_time":0.7601130349,"remaining_time":1.954576375},
{"learn":[4.514012334],"iteration":280,"passed_time":0.7619385057,"remaining_time":1.949586426},
{"learn":[4.508331416],"iteration":281,"passed_time":0.7649193626,"remaining_time":1.947560647},
{"learn":[4.506038537],"iteration":282,"passed_time":0.7673071371,"remaining_time":1.944025503},
{"learn":[4.505805643],"iteration":283,"passed_time":0.7691400238,"remaining_time":1.939099497},
{"learn":[4.501550352],"iteration":284,"passed_time":0.7712214732,"remaining_time":1.934818784},
{"learn":[4.494692643],"iteration":285,"passed_time":0.7729800653,"remaining_time":1.929747436},
{"learn":[4.489330245],"iteration":286,"passed_time":0.7747686958,"remaining_time":1.924773798},
{"learn":[4.484826955],"iteration":287,"passed_time":0.7764310567,"remaining_time":1.919510112},
{"learn":[4.478285428],"iteration":288,"passed_time":0.7802277126,"remaining_time":1.919522158},
{"learn":[4.475311671],"iteration":289,"passed_time":0.7835717799,"remaining_time":1.918399875},
{"learn":[4.471581298],"iteration":290,"passed_time":0.7858538721,"remaining_time":1.914674898},
{"learn":[4.469164956],"iteration":291,"passed_time":0.7880796336,"remaining_time":1.910823221},
{"learn":[4.462068024],"iteration":292,"passed_time":0.7902452808,"remaining_time":1.906837589},
{"learn":[4.458540976],"iteration":293,"passed_time":0.7923042217,"remaining_time":1.902608097},
{"learn":[4.455757458],"iteration":294,"passed_time":0.7955596779,"remaining_time":1.901252789},
{"learn":[4.453027414],"iteration":295,"passed_time":0.7976991324,"remaining_time":1.897230369},
{"learn":[4.450659338],"iteration":296,"passed_time":0.7997836916,"remaining_time":1.893090691},
{"learn":[4.444696901],"iteration":297,"passed_time":0.8014112463,"remaining_time":1.887888238},
{"learn":[4.442052813],"iteration":298,"passed_time":0.8035166688,"remaining_time":1.88383005},
{"learn":[4.440036756],"iteration":299,"passed_time":0.8056022273,"remaining_time":1.87973853},
{"learn":[4.435017051],"iteration":300,"passed_time":0.8074376223,"remaining_time":1.875079395},
{"learn":[4.429962125],"iteration":301,"passed_time":0.8097529884,"remaining_time":1.871548298},
{"learn":[4.427666256],"iteration":302,"passed_time":0.8126113716,"remaining_time":1.869274343},
{"learn":[4.425030004],"iteration":303,"passed_time":0.8146328136,"remaining_time":1.865080389},
{"learn":[4.422588771],"iteration":304,"passed_time":0.8166429606,"remaining_time":1.860874943},
{"learn":[4.418936667],"iteration":305,"passed_time":0.8188436797,"remaining_time":1.857116058},
{"learn":[4.416887976],"iteration":306,"passed_time":0.8207357851,"remaining_time":1.852670681},
{"learn":[4.413773354],"iteration":307,"passed_time":0.8227080398,"remaining_time":1.84842196},
{"learn":[4.411129391],"iteration":308,"passed_time":0.8250359393,"remaining_time":1.844983282},
{"learn":[4.40850819],"iteration":309,"passed_time":0.8272063524,"remaining_time":1.841201236},
{"learn":[4.404880292],"iteration":310,"passed_time":0.8291577231,"remaining_time":1.83694428},
{"learn":[4.404593827],"iteration":311,"passed_time":0.8307681214,"remaining_time":1.831950216},
{"learn":[4.402139942],"iteration":312,"passed_time":0.8327147876,"remaining_time":1.827715844},
{"learn":[4.400284725],"iteration":313,"passed_time":0.8345781319,"remaining_time":1.823314008},
{"learn":[4.395805521],"iteration":314,"passed_time":0.8367998513,"remaining_time":1.819707613},
{"learn":[4.392838833],"iteration":315,"passed_time":0.8398524522,"remaining_time":1.817908473},
{"learn":[4.389213061],"iteration":316,"passed_time":0.8420633086,"remaining_time":1.814287823},
{"learn":[4.3861981],"iteration":317,"passed_time":0.8441674231,"remaining_time":1.810447115},
{"learn":[4.385054234],"iteration":318,"passed_time":0.8459609024,"remaining_time":1.805954152},
{"learn":[4.379364607],"iteration":319,"passed_time":0.8476942317,"remaining_time":1.801350242},
{"learn":[4.378387619],"iteration":320,"passed_time":0.8494200944,"remaining_time":1.796748424},
{"learn":[4.375816727],"iteration":321,"passed_time":0.851492385,"remaining_time":1.792893904},
{"learn":[4.374600202],"iteration":322,"passed_time":0.8534844762,"remaining_time":1.788882323},
{"learn":[4.37098897],"iteration":323,"passed_time":0.8556098952,"remaining_time":1.785161386},
{"learn":[4.367418484],"iteration":324,"passed_time":0.8577528472,"remaining_time":1.781486683},
{"learn":[4.363584638],"iteration":325,"passed_time":0.8594289264,"remaining_time":1.776856124},
{"learn":[4.360770706],"iteration":326,"passed_time":0.8612352231,"remaining_time":1.772511637},
{"learn":[4.358675808],"iteration":327,"passed_time":0.8635464484,"remaining_time":1.769217114},
{"learn":[4.354228195],"iteration":328,"passed_time":0.8656592023,"remaining_time":1.765523783},
{"learn":[4.353773425],"iteration":329,"passed_time":0.8674565401,"remaining_time":1.761199642},
{"learn":[4.351648009],"iteration":330,"passed_time":0.8698566498,"remaining_time":1.758109059},
{"learn":[4.348209927],"iteration":331,"passed_time":0.8717837374,"remaining_time":1.754070893},
{"learn":[4.345852733],"iteration":332,"passed_time":0.8735568816,"remaining_time":1.749737057},
{"learn":[4.34237339],"iteration":333,"passed_time":0.8754528159,"remaining_time":1.745663399},
{"learn":[4.340814362],"iteration":334,"passed_time":0.8775549254,"remaining_time":1.742012016},
{"learn":[4.339707068],"iteration":335,"passed_time":0.879286234,"remaining_time":1.737637081},
{"learn":[4.335430786],"iteration":336,"passed_time":0.8809248621,"remaining_time":1.7330955},
{"learn":[4.33521887],"iteration":337,"passed_time":0.8827157648,"remaining_time":1.728869338},
{"learn":[4.328507238],"iteration":338,"passed_time":0.8852988951,"remaining_time":1.72620227},
{"learn":[4.326140732],"iteration":339,"passed_time":0.8873641578,"remaining_time":1.722530424},
{"learn":[4.323785636],"iteration":340,"passed_time":0.889156442,"remaining_time":1.718340455},
{"learn":[4.320632534],"iteration":341,"passed_time":0.8909698298,"remaining_time":1.714205111},
{"learn":[4.31973724],"iteration":342,"passed_time":0.8927905383,"remaining_time":1.710097328},
{"learn":[4.318000924],"iteration":343,"passed_time":0.8945408812,"remaining_time":1.705868657},
{"learn":[4.312713628],"iteration":344,"passed_time":0.8964994961,"remaining_time":1.702049768},
{"learn":[4.308220789],"iteration":345,"passed_time":0.8991045433,"remaining_time":1.699463501},
{"learn":[4.305890947],"iteration":346,"passed_time":0.9010555926,"remaining_time":1.695646403},
{"learn":[4.305137856],"iteration":347,"passed_time":0.9037000958,"remaining_time":1.69313926},
{"learn":[4.304787172],"iteration":348,"passed_time":0.9056453938,"remaining_time":1.689327081},
{"learn":[4.30350134],"iteration":349,"passed_time":0.907503685,"remaining_time":1.685363986},
{"learn":[4.30293809],"iteration":350,"passed_time":0.9100945206,"remaining_time":1.682767361},
{"learn":[4.299548459],"iteration":351,"passed_time":0.9122427485,"remaining_time":1.679355969},
{"learn":[4.294768408],"iteration":352,"passed_time":0.9145023732,"remaining_time":1.676155908},
{"learn":[4.294581479],"iteration":353,"passed_time":0.916909342,"remaining_time":1.673230042},
{"learn":[4.292551604],"iteration":354,"passed_time":0.9190025625,"remaining_time":1.66973705},
{"learn":[4.288628894],"iteration":355,"passed_time":0.9212703843,"remaining_time":1.666567774},
{"learn":[4.287802767],"iteration":356,"passed_time":0.9231057907,"remaining_time":1.662624716},
{"learn":[4.284566905],"iteration":357,"passed_time":0.9249777787,"remaining_time":1.658759033},
{"learn":[4.27890232],"iteration":358,"passed_time":0.9269156103,"remaining_time":1.655022023},
{"learn":[4.276938023],"iteration":359,"passed_time":0.9294493471,"remaining_time":1.652354395},
{"learn":[4.273425094],"iteration":360,"passed_time":0.931513379,"remaining_time":1.648856092},
{"learn":[4.269726505],"iteration":361,"passed_time":0.9339652382,"remaining_time":1.646049232},
{"learn":[4.265565857],"iteration":362,"passed_time":0.9358745173,"remaining_time":1.642292197},
{"learn":[4.262117173],"iteration":363,"passed_time":0.9377217848,"remaining_time":1.638436965},
{"learn":[4.259185148],"iteration":364,"passed_time":0.9395768762,"remaining_time":1.634606346},
{"learn":[4.257668507],"iteration":365,"passed_time":0.9413455589,"remaining_time":1.630636842},
{"learn":[4.253432436],"iteration":366,"passed_time":0.9433971875,"remaining_time":1.627167356},
{"learn":[4.250216667],"iteration":367,"passed_time":0.9457257705,"remaining_time":1.624181215},
{"learn":[4.24514828],"iteration":368,"passed_time":0.9478510307,"remaining_time":1.62085095},
{"learn":[4.244015772],"iteration":369,"passed_time":0.950129847,"remaining_time":1.617788658},
{"learn":[4.240329192],"iteration":370,"passed_time":0.9523385741,"remaining_time":1.61461176},
{"learn":[4.236718014],"iteration":371,"passed_time":0.9541997508,"remaining_time":1.610853343},
{"learn":[4.233495944],"iteration":372,"passed_time":0.9562459715,"remaining_time":1.607416151},
{"learn":[4.230357491],"iteration":373,"passed_time":0.958848264,"remaining_time":1.604917148},
{"learn":[4.227381215],"iteration":374,"passed_time":0.9613126965,"remaining_time":1.602187827},
{"learn":[4.226169067],"iteration":375,"passed_time":0.9631477164,"remaining_time":1.598415359},
{"learn":[4.225963861],"iteration":376,"passed_time":0.9650469542,"remaining_time":1.59475929},
{"learn":[4.224346548],"iteration":377,"passed_time":0.9669737058,"remaining_time":1.591157791},
{"learn":[4.222595381],"iteration":378,"passed_time":0.9688476035,"remaining_time":1.587478527},
{"learn":[4.219700938],"iteration":379,"passed_time":0.970836622,"remaining_time":1.583996594},
{"learn":[4.216356207],"iteration":380,"passed_time":0.9730508856,"remaining_time":1.580888447},
{"learn":[4.214326494],"iteration":381,"passed_time":0.9751816704,"remaining_time":1.577649928},
{"learn":[4.212901398],"iteration":382,"passed_time":0.9773647704,"remaining_time":1.574501471},
{"learn":[4.211331091],"iteration":383,"passed_time":0.9795913106,"remaining_time":1.571427727},
{"learn":[4.208624791],"iteration":384,"passed_time":0.9813007012,"remaining_time":1.567532289},
{"learn":[4.204659106],"iteration":385,"passed_time":0.9832102007,"remaining_time":1.563966485},
{"learn":[4.202968852],"iteration":386,"passed_time":0.9847829401,"remaining_time":1.55987582},
{"learn":[4.197261935],"iteration":387,"passed_time":0.9869302648,"remaining_time":1.556704438},
{"learn":[4.196934403],"iteration":388,"passed_time":0.989293452,"remaining_time":1.553877376},
{"learn":[4.192479929],"iteration":389,"passed_time":0.9912912944,"remaining_time":1.550481255},
{"learn":[4.190243116],"iteration":390,"passed_time":0.9931368826,"remaining_time":1.546855145},
{"learn":[4.185852431],"iteration":391,"passed_time":0.9947350203,"remaining_time":1.542854317},
{"learn":[4.180967944],"iteration":392,"passed_time":0.9965702913,"remaining_time":1.539231977},
{"learn":[4.178283162],"iteration":393,"passed_time":0.9983014958,"remaining_time":1.535458646},
{"learn":[4.176341157],"iteration":394,"passed_time":1.000215184,"remaining_time":1.531975155},
{"learn":[4.176041504],"iteration":395,"passed_time":1.002694697,"remaining_time":1.529362619},
{"learn":[4.175564513],"iteration":396,"passed_time":1.004827325,"remaining_time":1.526223871},
{"learn":[4.170830274],"iteration":397,"passed_time":1.007004523,"remaining_time":1.523157595},
{"learn":[4.167804808],"iteration":398,"passed_time":1.00887652,"remaining_time":1.519636062},
{"learn":[4.165860548],"iteration":399,"passed_time":1.010817864,"remaining_time":1.516226796},
{"learn":[4.160950571],"iteration":400,"passed_time":1.012584093,"remaining_time":1.512563271},
{"learn":[4.158544115],"iteration":401,"passed_time":1.015249483,"remaining_time":1.510246744},
{"learn":[4.154448767],"iteration":402,"passed_time":1.017597815,"remaining_time":1.507458798},
{"learn":[4.15197457],"iteration":403,"passed_time":1.019901366,"remaining_time":1.504606966},
{"learn":[4.149562679],"iteration":404,"passed_time":1.021878595,"remaining_time":1.50127843},
{"learn":[4.149327961],"iteration":405,"passed_time":1.023728087,"remaining_time":1.497769664},
{"learn":[4.147444889],"iteration":406,"passed_time":1.025567897,"remaining_time":1.494254946},
{"learn":[4.147254809],"iteration":407,"passed_time":1.027578593,"remaining_time":1.49099639},
{"learn":[4.144589165],"iteration":408,"passed_time":1.02977467,"remaining_time":1.488011809},
{"learn":[4.141691034],"iteration":409,"passed_time":1.032358567,"remaining_time":1.485589158},
{"learn":[4.138893468],"iteration":410,"passed_time":1.034519559,"remaining_time":1.48255966},
{"learn":[4.136964597],"iteration":411,"passed_time":1.036345511,"remaining_time":1.479056214},
{"learn":[4.133773523],"iteration":412,"passed_time":1.038592623,"remaining_time":1.476159491},
{"learn":[4.131363444],"iteration":413,"passed_time":1.041436959,"remaining_time":1.474111252},
{"learn":[4.130228592],"iteration":414,"passed_time":1.043720036,"remaining_time":1.471268002},
{"learn":[4.12884186],"iteration":415,"passed_time":1.045413163,"remaining_time":1.467599248},
{"learn":[4.12413494],"iteration":416,"passed_time":1.048630987,"remaining_time":1.46607162},
{"learn":[4.119422508],"iteration":417,"passed_time":1.051068417,"remaining_time":1.463449327},
{"learn":[4.117038244],"iteration":418,"passed_time":1.053368117,"remaining_time":1.460636936},
{"learn":[4.116067631],"iteration":419,"passed_time":1.055938032,"remaining_time":1.458200139},
{"learn":[4.110343455],"iteration":420,"passed_time":1.059315134,"remaining_time":1.456872833},
{"learn":[4.105604544],"iteration":421,"passed_time":1.061296208,"remaining_time":1.453623716},
{"learn":[4.103390131],"iteration":422,"passed_time":1.06386914,"remaining_time":1.451187929},
{"learn":[4.096724402],"iteration":423,"passed_time":1.066031199,"remaining_time":1.448193326},
{"learn":[4.093431279],"iteration":424,"passed_time":1.068546738,"remaining_time":1.445680881},
{"learn":[4.091412744],"iteration":425,"passed_time":1.070518737,"remaining_time":1.442436044},
{"learn":[4.091192901],"iteration":426,"passed_time":1.072454843,"remaining_time":1.439149005},
{"learn":[4.088994581],"iteration":427,"passed_time":1.074362409,"remaining_time":1.435830135},
{"learn":[4.087845355],"iteration":428,"passed_time":1.076330555,"remaining_time":1.432598478},
{"learn":[4.083650279],"iteration":429,"passed_time":1.07930006,"remaining_time":1.43070008},
{"learn":[4.079840652],"iteration":430,"passed_time":1.082460287,"remaining_time":1.429048499},
{"learn":[4.075707828],"iteration":431,"passed_time":1.08486123,"remaining_time":1.426391617},
{"learn":[4.071345409],"iteration":432,"passed_time":1.086833184,"remaining_time":1.42317417},
{"learn":[4.067460475],"iteration":433,"passed_time":1.088981398,"remaining_time":1.42019233},
{"learn":[4.064914749],"iteration":434,"passed_time":1.090865151,"remaining_time":1.416870828},
{"learn":[4.063823175],"iteration":435,"passed_time":1.092762901,"remaining_time":1.413574027},
{"learn":[4.058898471],"iteration":436,"passed_time":1.095304711,"remaining_time":1.411113392},
{"learn":[4.054120355],"iteration":437,"passed_time":1.097715837,"remaining_time":1.408484703},
{"learn":[4.052715901],"iteration":438,"passed_time":1.099838541,"remaining_time":1.405488432},
{"learn":[4.052114167],"iteration":439,"passed_time":1.102030429,"remaining_time":1.402584182},
{"learn":[4.051377267],"iteration":440,"passed_time":1.103869781,"remaining_time":1.399236298},
{"learn":[4.049275336],"iteration":441,"passed_time":1.105702729,"remaining_time":1.395887156},
{"learn":[4.047099198],"iteration":442,"passed_time":1.109768273,"remaining_time":1.395351983},
{"learn":[4.044348685],"iteration":443,"passed_time":1.111829569,"remaining_time":1.392291082},
{"learn":[4.042822379],"iteration":444,"passed_time":1.113946322,"remaining_time":1.38930384},
{"learn":[4.041258611],"iteration":445,"passed_time":1.115928099,"remaining_time":1.38615284},
{"learn":[4.040044254],"iteration":446,"passed_time":1.11792275,"remaining_time":1.383023},
{"learn":[4.036860137],"iteration":447,"passed_time":1.12034602,"remaining_time":1.380426346},
{"learn":[4.036372284],"iteration":448,"passed_time":1.123802407,"remaining_time":1.379098276},
{"learn":[4.03368231],"iteration":449,"passed_time":1.126112991,"remaining_time":1.376360322},
{"learn":[4.032439519],"iteration":450,"passed_time":1.128066414,"remaining_time":1.373189493},
{"learn":[4.032008634],"iteration":451,"passed_time":1.13001051,"remaining_time":1.370012742},
{"learn":[4.030034932],"iteration":452,"passed_time":1.13173256,"remaining_time":1.366573312},
{"learn":[4.028173412],"iteration":453,"passed_time":1.133583285,"remaining_time":1.363296198},
{"learn":[4.023806097],"iteration":454,"passed_time":1.13523751,"remaining_time":1.359789985},
{"learn":[4.020239186],"iteration":455,"passed_time":1.138548243,"remaining_time":1.358268079},
{"learn":[4.017384838],"iteration":456,"passed_time":1.141500465,"remaining_time":1.356312369},
{"learn":[4.016468229],"iteration":457,"passed_time":1.144300809,"remaining_time":1.354172573},
{"learn":[4.014530169],"iteration":458,"passed_time":1.146446946,"remaining_time":1.351258818},
{"learn":[4.012884822],"iteration":459,"passed_time":1.148100704,"remaining_time":1.347770392},
{"learn":[4.008924707],"iteration":460,"passed_time":1.149843566,"remaining_time":1.344394105},
{"learn":[4.008286778],"iteration":461,"passed_time":1.153241652,"remaining_time":1.3429524},
{"learn":[4.006444202],"iteration":462,"passed_time":1.155820626,"remaining_time":1.340552217},
{"learn":[4.003284363],"iteration":463,"passed_time":1.158131764,"remaining_time":1.337841866},
{"learn":[3.999811484],"iteration":464,"passed_time":1.160313041,"remaining_time":1.334983822},
{"learn":[3.997483319],"iteration":465,"passed_time":1.162404134,"remaining_time":1.332025338},
{"learn":[3.99708333],"iteration":466,"passed_time":1.164609001,"remaining_time":1.329200423},
{"learn":[3.995860263],"iteration":467,"passed_time":1.166780204,"remaining_time":1.32633989},
{"learn":[3.994131111],"iteration":468,"passed_time":1.169286759,"remaining_time":1.323861981},
{"learn":[3.993125499],"iteration":469,"passed_time":1.171781762,"remaining_time":1.321370923},
{"learn":[3.992954084],"iteration":470,"passed_time":1.174016702,"remaining_time":1.318587761},
{"learn":[3.990635743],"iteration":471,"passed_time":1.176211762,"remaining_time":1.31576231},
{"learn":[3.986678254],"iteration":472,"passed_time":1.178589482,"remaining_time":1.313143038},
{"learn":[3.986393291],"iteration":473,"passed_time":1.180504608,"remaining_time":1.310011443},
{"learn":[3.986152671],"iteration":474,"passed_time":1.183153238,"remaining_time":1.307695684},
{"learn":[3.985596662],"iteration":475,"passed_time":1.185130227,"remaining_time":1.304639157},
{"learn":[3.983853457],"iteration":476,"passed_time":1.187040689,"remaining_time":1.301514215},
{"learn":[3.983263928],"iteration":477,"passed_time":1.18898619,"remaining_time":1.298432617},
{"learn":[3.980067202],"iteration":478,"passed_time":1.19107218,"remaining_time":1.295508572},
{"learn":[3.978115407],"iteration":479,"passed_time":1.194270425,"remaining_time":1.29379296},
{"learn":[3.972661644],"iteration":480,"passed_time":1.196505545,"remaining_time":1.291031971},
{"learn":[3.969938254],"iteration":481,"passed_time":1.199239419,"remaining_time":1.288809168},
{"learn":[3.968211434],"iteration":482,"passed_time":1.201707668,"remaining_time":1.286299926},
{"learn":[3.966113368],"iteration":483,"passed_time":1.204170355,"remaining_time":1.283784924},
{"learn":[3.962246044],"iteration":484,"passed_time":1.20611778,"remaining_time":1.280723003},
{"learn":[3.961319703],"iteration":485,"passed_time":1.208446221,"remaining_time":1.278068637},
{"learn":[3.96078191],"iteration":486,"passed_time":1.210538211,"remaining_time":1.275166535},
{"learn":[3.958913633],"iteration":487,"passed_time":1.21328811,"remaining_time":1.272958017},
{"learn":[3.957428286],"iteration":488,"passed_time":1.215921194,"remaining_time":1.270625215},
{"learn":[3.952641965],"iteration":489,"passed_time":1.218173745,"remaining_time":1.267895122},
{"learn":[3.951486786],"iteration":490,"passed_time":1.22031338,"remaining_time":1.265049919},
{"learn":[3.94938344],"iteration":491,"passed_time":1.222305669,"remaining_time":1.262055447},
{"learn":[3.947297924],"iteration":492,"passed_time":1.224525271,"remaining_time":1.259298808},
{"learn":[3.946284886],"iteration":493,"passed_time":1.227193361,"remaining_time":1.257003726},
{"learn":[3.943288204],"iteration":494,"passed_time":1.229326874,"remaining_time":1.254161761},
{"learn":[3.943076488],"iteration":495,"passed_time":1.231268991,"remaining_time":1.251128169},
{"learn":[3.942347078],"iteration":496,"passed_time":1.233383363,"remaining_time":1.248273303},
{"learn":[3.940251541],"iteration":497,"passed_time":1.235326719,"remaining_time":1.245249022},
{"learn":[3.939011019],"iteration":498,"passed_time":1.237041706,"remaining_time":1.241999789},
{"learn":[3.938760512],"iteration":499,"passed_time":1.238843359,"remaining_time":1.238843359},
{"learn":[3.934522727],"iteration":500,"passed_time":1.242119111,"remaining_time":1.237160552},
{"learn":[3.930091193],"iteration":501,"passed_time":1.244556773,"remaining_time":1.234639986},
{"learn":[3.927671752],"iteration":502,"passed_time":1.247251213,"remaining_time":1.232373465},
{"learn":[3.927280041],"iteration":503,"passed_time":1.249488688,"remaining_time":1.229655535},
{"learn":[3.925987561],"iteration":504,"passed_time":1.251299941,"remaining_time":1.226521724},
{"learn":[3.921645957],"iteration":505,"passed_time":1.253356438,"remaining_time":1.22363257},
{"learn":[3.920333743],"iteration":506,"passed_time":1.255727505,"remaining_time":1.221052584},
{"learn":[3.918659461],"iteration":507,"passed_time":1.258287002,"remaining_time":1.218655916},
{"learn":[3.916124385],"iteration":508,"passed_time":1.262084131,"remaining_time":1.217452472},
{"learn":[3.913849268],"iteration":509,"passed_time":1.264242988,"remaining_time":1.214664832},
{"learn":[3.912826119],"iteration":510,"passed_time":1.266369113,"remaining_time":1.211848329},
{"learn":[3.910034145],"iteration":511,"passed_time":1.268223318,"remaining_time":1.20877535},
{"learn":[3.90792379],"iteration":512,"passed_time":1.270511348,"remaining_time":1.20611896},
{"learn":[3.907823851],"iteration":513,"passed_time":1.272308057,"remaining_time":1.202999446},
{"learn":[3.904527401],"iteration":514,"passed_time":1.274258194,"remaining_time":1.200029562},
{"learn":[3.903378283],"iteration":515,"passed_time":1.276428434,"remaining_time":1.197270082},
{"learn":[3.902170135],"iteration":516,"passed_time":1.27853608,"remaining_time":1.194454404},
{"learn":[3.899435429],"iteration":517,"passed_time":1.280701745,"remaining_time":1.191695446},
{"learn":[3.897497505],"iteration":518,"passed_time":1.282415085,"remaining_time":1.188519568},
{"learn":[3.896426119],"iteration":519,"passed_time":1.283960069,"remaining_time":1.18519391},
{"learn":[3.896044669],"iteration":520,"passed_time":1.286504773,"remaining_time":1.182794215},
{"learn":[3.892795942],"iteration":521,"passed_time":1.28913399,"remaining_time":1.180471355},
{"learn":[3.892413888],"iteration":522,"passed_time":1.290891132,"remaining_time":1.17735195},
{"learn":[3.891738985],"iteration":523,"passed_time":1.292919233,"remaining_time":1.174483883},
{"learn":[3.88822057],"iteration":524,"passed_time":1.294781347,"remaining_time":1.171468838},
{"learn":[3.883837053],"iteration":525,"passed_time":1.296655372,"remaining_time":1.168468909},
{"learn":[3.881769742],"iteration":526,"passed_time":1.298790108,"remaining_time":1.16570725},
{"learn":[3.880356898],"iteration":527,"passed_time":1.301311783,"remaining_time":1.163293866},
{"learn":[3.879250273],"iteration":528,"passed_time":1.303852795,"remaining_time":1.16089729},
{"learn":[3.877174493],"iteration":529,"passed_time":1.306275818,"remaining_time":1.158395537},
{"learn":[3.875854201],"iteration":530,"passed_time":1.308130392,"remaining_time":1.155392004},
{"learn":[3.873189396],"iteration":531,"passed_time":1.309883942,"remaining_time":1.152303919},
{"learn":[3.871583368],"iteration":532,"passed_time":1.311793829,"remaining_time":1.14935782},
{"learn":[3.869622679],"iteration":533,"passed_time":1.313644169,"remaining_time":1.146363639},
{"learn":[3.866860164],"iteration":534,"passed_time":1.316036663,"remaining_time":1.14384495},
{"learn":[3.864498444],"iteration":535,"passed_time":1.318878962,"remaining_time":1.141716117},
{"learn":[3.861416322],"iteration":536,"passed_time":1.320813453,"remaining_time":1.138801916},
{"learn":[3.860265769],"iteration":537,"passed_time":1.322701052,"remaining_time":1.13585109},
{"learn":[3.859328725],"iteration":538,"passed_time":1.324636231,"remaining_time":1.132944903},
{"learn":[3.858521278],"iteration":539,"passed_time":1.326450158,"remaining_time":1.129939023},
{"learn":[3.85599111],"iteration":540,"passed_time":1.328024682,"remaining_time":1.126734434},
{"learn":[3.852379816],"iteration":541,"passed_time":1.329860344,"remaining_time":1.123756527},
{"learn":[3.851327537],"iteration":542,"passed_time":1.332200023,"remaining_time":1.121207018},
{"learn":[3.847854898],"iteration":543,"passed_time":1.334055955,"remaining_time":1.118252786},
{"learn":[3.847083414],"iteration":544,"passed_time":1.335737356,"remaining_time":1.115156875},
{"learn":[3.845397429],"iteration":545,"passed_time":1.337516018,"remaining_time":1.112147018},
{"learn":[3.841933528],"iteration":546,"passed_time":1.339361723,"remaining_time":1.109197186},
{"learn":[3.840996474],"iteration":547,"passed_time":1.341338424,"remaining_time":1.10635943},
{"learn":[3.838355966],"iteration":548,"passed_time":1.343649592,"remaining_time":1.103799573},
{"learn":[3.83342799],"iteration":549,"passed_time":1.346408182,"remaining_time":1.101606694},
{"learn":[3.828161535],"iteration":550,"passed_time":1.34901058,"remaining_time":1.099284484},
{"learn":[3.823502399],"iteration":551,"passed_time":1.351084471,"remaining_time":1.096532324},
{"learn":[3.820068862],"iteration":552,"passed_time":1.35368372,"remaining_time":1.094207275},
{"learn":[3.817951642],"iteration":553,"passed_time":1.355809379,"remaining_time":1.091499969},
{"learn":[3.815785958],"iteration":554,"passed_time":1.357986287,"remaining_time":1.088835852},
{"learn":[3.81503012],"iteration":555,"passed_time":1.360792035,"remaining_time":1.086675654},
{"learn":[3.813529315],"iteration":556,"passed_time":1.362886878,"remaining_time":1.083947732},
{"learn":[3.808881326],"iteration":557,"passed_time":1.365069143,"remaining_time":1.081291329},
{"learn":[3.808740434],"iteration":558,"passed_time":1.366873616,"remaining_time":1.078338577},
{"learn":[3.80714352],"iteration":559,"passed_time":1.368662052,"remaining_time":1.075377326},
{"learn":[3.80573346],"iteration":560,"passed_time":1.370447631,"remaining_time":1.072418022},
{"learn":[3.803370052],"iteration":561,"passed_time":1.372650794,"remaining_time":1.069788341},
{"learn":[3.803215211],"iteration":562,"passed_time":1.374496565,"remaining_time":1.066882769},
{"learn":[3.801309667],"iteration":563,"passed_time":1.376943567,"remaining_time":1.064445736},
{"learn":[3.800003847],"iteration":564,"passed_time":1.378759657,"remaining_time":1.061522922},
{"learn":[3.798026138],"iteration":565,"passed_time":1.380460145,"remaining_time":1.058515376},
{"learn":[3.794745847],"iteration":566,"passed_time":1.38245985,"remaining_time":1.055740943},
{"learn":[3.794312041],"iteration":567,"passed_time":1.384258987,"remaining_time":1.052816694},
{"learn":[3.792205926],"iteration":568,"passed_time":1.386211677,"remaining_time":1.050012711},
{"learn":[3.788991061],"iteration":569,"passed_time":1.388388501,"remaining_time":1.047380799},
{"learn":[3.787391572],"iteration":570,"passed_time":1.391135114,"remaining_time":1.045178571},
{"learn":[3.7826445],"iteration":571,"passed_time":1.393264939,"remaining_time":1.042512926},
{"learn":[3.781700331],"iteration":572,"passed_time":1.395262722,"remaining_time":1.039750754},
{"learn":[3.780045374],"iteration":573,"passed_time":1.397207325,"remaining_time":1.036951778},
{"learn":[3.775462644],"iteration":574,"passed_time":1.398946237,"remaining_time":1.034003741},
{"learn":[3.773711943],"iteration":575,"passed_time":1.401380425,"remaining_time":1.031571702},
{"learn":[3.772415806],"iteration":576,"passed_time":1.403035968,"remaining_time":1.028568829},
{"learn":[3.770170875],"iteration":577,"passed_time":1.404788374,"remaining_time":1.025641339},
{"learn":[3.765166479],"iteration":578,"passed_time":1.407306342,"remaining_time":1.02327456},
{"learn":[3.763976102],"iteration":579,"passed_time":1.409161293,"remaining_time":1.020427143},
{"learn":[3.760761708],"iteration":580,"passed_time":1.410860105,"remaining_time":1.01747054},
{"learn":[3.758155662],"iteration":581,"passed_time":1.412739957,"remaining_time":1.014648285},
{"learn":[3.756844548],"iteration":582,"passed_time":1.414730812,"remaining_time":1.01190866},
{"learn":[3.753098923],"iteration":583,"passed_time":1.416351656,"remaining_time":1.008908029},
{"learn":[3.751618946],"iteration":584,"passed_time":1.418065679,"remaining_time":1.005978217},
{"learn":[3.751398464],"iteration":585,"passed_time":1.419541142,"remaining_time":1.002884015},
{"learn":[3.749920103],"iteration":586,"passed_time":1.421624254,"remaining_time":1.000222856},
{"learn":[3.748237465],"iteration":587,"passed_time":1.423584927,"remaining_time":0.9974778743},
{"learn":[3.746021536],"iteration":588,"passed_time":1.425442168,"remaining_time":0.9946633804},
{"learn":[3.74417648],"iteration":589,"passed_time":1.428080063,"remaining_time":0.9923946202},
{"learn":[3.738788389],"iteration":590,"passed_time":1.431060057,"remaining_time":0.990361359},
{"learn":[3.736021611],"iteration":591,"passed_time":1.432737215,"remaining_time":0.9874269993},
{"learn":[3.734546151],"iteration":592,"passed_time":1.434511031,"remaining_time":0.9845632205},
{"learn":[3.733527479],"iteration":593,"passed_time":1.436722235,"remaining_time":0.9820020662},
{"learn":[3.733026392],"iteration":594,"passed_time":1.438614783,"remaining_time":0.9792251884},
{"learn":[3.730314752],"iteration":595,"passed_time":1.440324503,"remaining_time":0.9763273475},
{"learn":[3.727342596],"iteration":596,"passed_time":1.44205521,"remaining_time":0.9734476541},
{"learn":[3.725459604],"iteration":597,"passed_time":1.443778843,"remaining_time":0.9705670484},
{"learn":[3.723158842],"iteration":598,"passed_time":1.44544541,"remaining_time":0.9676521025},
{"learn":[3.722362756],"iteration":599,"passed_time":1.447207026,"remaining_time":0.964804684},
{"learn":[3.721443615],"iteration":600,"passed_time":1.448741338,"remaining_time":0.9618099733},
{"learn":[3.720743486],"iteration":601,"passed_time":1.450367461,"remaining_time":0.9588808132},
{"learn":[3.720215334],"iteration":602,"passed_time":1.452293303,"remaining_time":0.9561533022},
{"learn":[3.719436563],"iteration":603,"passed_time":1.454214896,"remaining_time":0.9534256606},
{"learn":[3.715046574],"iteration":604,"passed_time":1.456267576,"remaining_time":0.9507862688},
{"learn":[3.71443396],"iteration":605,"passed_time":1.458280505,"remaining_time":0.9481229687},
{"learn":[3.712938941],"iteration":606,"passed_time":1.459933586,"remaining_time":0.9452288294},
{"learn":[3.712814764],"iteration":607,"passed_time":1.461649821,"remaining_time":0.9423794899},
{"learn":[3.71235348],"iteration":608,"passed_time":1.463503724,"remaining_time":0.9396222595},
{"learn":[3.711223749],"iteration":609,"passed_time":1.465476254,"remaining_time":0.9369438346},
{"learn":[3.710755648],"iteration":610,"passed_time":1.467680483,"remaining_time":0.9344152338},
{"learn":[3.708668039],"iteration":611,"passed_time":1.469862646,"remaining_time":0.9318737037},
{"learn":[3.705623591],"iteration":612,"passed_time":1.472039666,"remaining_time":0.9293300988},
{"learn":[3.704045802],"iteration":613,"passed_time":1.474826165,"remaining_time":0.9271708462},
{"learn":[3.699915209],"iteration":614,"passed_time":1.476740701,"remaining_time":0.9244636906},
{"learn":[3.696182221],"iteration":615,"passed_time":1.482916344,"remaining_time":0.9244153831},
{"learn":[3.694263278],"iteration":616,"passed_time":1.484846242,"remaining_time":0.9217116864},
{"learn":[3.693810229],"iteration":617,"passed_time":1.486719351,"remaining_time":0.9189753914},
{"learn":[3.690900932],"iteration":618,"passed_time":1.488377227,"remaining_time":0.9161094076},
{"learn":[3.688020895],"iteration":619,"passed_time":1.490167928,"remaining_time":0.9133287298},
{"learn":[3.685491894],"iteration":620,"passed_time":1.491888475,"remaining_time":0.9105084251},
{"learn":[3.684328128],"iteration":621,"passed_time":1.493437643,"remaining_time":0.9075875068},
{"learn":[3.680640153],"iteration":622,"passed_time":1.495482371,"remaining_time":0.9049708729},
{"learn":[3.678932783],"iteration":623,"passed_time":1.497519479,"remaining_time":0.9023514808},
{"learn":[3.674167041],"iteration":624,"passed_time":1.499387686,"remaining_time":0.8996326119},
{"learn":[3.672200976],"iteration":625,"passed_time":1.501358273,"remaining_time":0.8969776261},
{"learn":[3.670606604],"iteration":626,"passed_time":1.502970633,"remaining_time":0.8941117162},
{"learn":[3.665506042],"iteration":627,"passed_time":1.504705014,"remaining_time":0.8913220785},
{"learn":[3.664214007],"iteration":628,"passed_time":1.506426517,"remaining_time":0.8885282001},
{"learn":[3.66261643],"iteration":629,"passed_time":1.508060848,"remaining_time":0.8856865298},
{"learn":[3.662118449],"iteration":630,"passed_time":1.509584796,"remaining_time":0.882784136},
{"learn":[3.660871366],"iteration":631,"passed_time":1.511504874,"remaining_time":0.8801167618},
{"learn":[3.656695243],"iteration":632,"passed_time":1.513423459,"remaining_time":0.8774508839},
{"learn":[3.654497801],"iteration":633,"passed_time":1.515243855,"remaining_time":0.8747306795},
{"learn":[3.654189134],"iteration":634,"passed_time":1.516852427,"remaining_time":0.8718915525},
{"learn":[3.653957699],"iteration":635,"passed_time":1.518634299,"remaining_time":0.8691554793},
{"learn":[3.651920725],"iteration":636,"passed_time":1.520447893,"remaining_time":0.8664404791},
{"learn":[3.65106705],"iteration":637,"passed_time":1.522251729,"remaining_time":0.8637227679},
{"learn":[3.650612844],"iteration":638,"passed_time":1.524270181,"remaining_time":0.8611291635},
{"learn":[3.649884732],"iteration":639,"passed_time":1.526471046,"remaining_time":0.8586399636},
{"learn":[3.646276182],"iteration":640,"passed_time":1.528730471,"remaining_time":0.8561844603},
{"learn":[3.645808194],"iteration":641,"passed_time":1.531007063,"remaining_time":0.8537391408},
{"learn":[3.645042989],"iteration":642,"passed_time":1.532775027,"remaining_time":0.8510119514},
{"learn":[3.639864499],"iteration":643,"passed_time":1.534943194,"remaining_time":0.8485089707},
{"learn":[3.637318478],"iteration":644,"passed_time":1.536669655,"remaining_time":0.8457639187},
{"learn":[3.636344905],"iteration":645,"passed_time":1.538418125,"remaining_time":0.8430340807},
{"learn":[3.634754643],"iteration":646,"passed_time":1.540223296,"remaining_time":0.8403382127},
{"learn":[3.630724975],"iteration":647,"passed_time":1.542144436,"remaining_time":0.8377080887},
{"learn":[3.629408252],"iteration":648,"passed_time":1.543934514,"remaining_time":0.8350092672},
{"learn":[3.62790646],"iteration":649,"passed_time":1.545620814,"remaining_time":0.8322573612},
{"learn":[3.627388973],"iteration":650,"passed_time":1.547519883,"remaining_time":0.8296227942},
{"learn":[3.625163557],"iteration":651,"passed_time":1.549223106,"remaining_time":0.8268859523},
{"learn":[3.623701985],"iteration":652,"passed_time":1.550865651,"remaining_time":0.824120032},
{"learn":[3.622342639],"iteration":653,"passed_time":1.552426523,"remaining_time":0.8213143378},
{"learn":[3.621130639],"iteration":654,"passed_time":1.554845431,"remaining_time":0.8189643874},
{"learn":[3.619125665],"iteration":655,"passed_time":1.55687661,"remaining_time":0.8164109052},
{"learn":[3.618878783],"iteration":656,"passed_time":1.558654654,"remaining_time":0.813726859},
{"learn":[3.616207429],"iteration":657,"passed_time":1.560459889,"remaining_time":0.8110596993},
{"learn":[3.61206486],"iteration":658,"passed_time":1.56226192,"remaining_time":0.8083934974},
{"learn":[3.611955873],"iteration":659,"passed_time":1.56378449,"remaining_time":0.8055859495},
{"learn":[3.610713743],"iteration":660,"passed_time":1.565557798,"remaining_time":0.8029108827},
{"learn":[3.610044025],"iteration":661,"passed_time":1.567511739,"remaining_time":0.8003307671},
{"learn":[3.607342669],"iteration":662,"passed_time":1.569457332,"remaining_time":0.7977482969},
{"learn":[3.602510618],"iteration":663,"passed_time":1.571946347,"remaining_time":0.7954427301},
{"learn":[3.600492392],"iteration":664,"passed_time":1.574191249,"remaining_time":0.7930136369},
{"learn":[3.597171065],"iteration":665,"passed_time":1.576167295,"remaining_time":0.7904502649},
{"learn":[3.594358798],"iteration":666,"passed_time":1.577833269,"remaining_time":0.7877338511},
{"learn":[3.593945251],"iteration":667,"passed_time":1.579544577,"remaining_time":0.7850431131},
{"learn":[3.593607748],"iteration":668,"passed_time":1.581115869,"remaining_time":0.7822860278},
{"learn":[3.592238714],"iteration":669,"passed_time":1.58284678,"remaining_time":0.7796111007},
{"learn":[3.590144654],"iteration":670,"passed_time":1.584715552,"remaining_time":0.7770065823},
{"learn":[3.587151536],"iteration":671,"passed_time":1.586927812,"remaining_time":0.7745719082},
{"learn":[3.586070865],"iteration":672,"passed_time":1.58870063,"remaining_time":0.7719243776},
{"learn":[3.585102746],"iteration":673,"passed_time":1.590366369,"remaining_time":0.7692276505},
{"learn":[3.584362847],"iteration":674,"passed_time":1.59219653,"remaining_time":0.766613144},
{"learn":[3.581407561],"iteration":675,"passed_time":1.593858728,"remaining_time":0.7639204556},
{"learn":[3.57919422],"iteration":676,"passed_time":1.595688248,"remaining_time":0.7613106413},
{"learn":[3.577632204],"iteration":677,"passed_time":1.597586729,"remaining_time":0.7587358803},
{"learn":[3.573911195],"iteration":678,"passed_time":1.599764287,"remaining_time":0.7562950457},
{"learn":[3.573408216],"iteration":679,"passed_time":1.601996098,"remaining_time":0.7538805166},
{"learn":[3.571076482],"iteration":680,"passed_time":1.60415096,"remaining_time":0.751430479},
{"learn":[3.568177107],"iteration":681,"passed_time":1.606115642,"remaining_time":0.7488926308},
{"learn":[3.564824621],"iteration":682,"passed_time":1.60776728,"remaining_time":0.7462111681},
{"learn":[3.562475026],"iteration":683,"passed_time":1.609315287,"remaining_time":0.7434848401},
{"learn":[3.561226889],"iteration":684,"passed_time":1.611124202,"remaining_time":0.7408819321},
{"learn":[3.559383467],"iteration":685,"passed_time":1.612966256,"remaining_time":0.7382965076},
{"learn":[3.555209766],"iteration":686,"passed_time":1.614630322,"remaining_time":0.7356321553},
{"learn":[3.55345383],"iteration":687,"passed_time":1.616513401,"remaining_time":0.7330700308},
{"learn":[3.552300968],"iteration":688,"passed_time":1.618278689,"remaining_time":0.7304567088},
{"learn":[3.551253986],"iteration":689,"passed_time":1.619914865,"remaining_time":0.7277878378},
{"learn":[3.549807725],"iteration":690,"passed_time":1.621541489,"remaining_time":0.7251176845},
{"learn":[3.547992926],"iteration":691,"passed_time":1.622993144,"remaining_time":0.7223726709},
{"learn":[3.545438607],"iteration":692,"passed_time":1.625049807,"remaining_time":0.7198994097},
{"learn":[3.543313763],"iteration":693,"passed_time":1.626824833,"remaining_time":0.7173031686},
{"learn":[3.542962896],"iteration":694,"passed_time":1.628592439,"remaining_time":0.7147060343},
{"learn":[3.539800465],"iteration":695,"passed_time":1.630545898,"remaining_time":0.712192461},
{"learn":[3.53953187],"iteration":696,"passed_time":1.63265555,"remaining_time":0.7097483953},
{"learn":[3.536332425],"iteration":697,"passed_time":1.634708591,"remaining_time":0.7072807943},
{"learn":[3.534993327],"iteration":698,"passed_time":1.636411164,"remaining_time":0.7046634628},
{"learn":[3.531637011],"iteration":699,"passed_time":1.6383388,"remaining_time":0.7021452},
{"learn":[3.531040284],"iteration":700,"passed_time":1.640246122,"remaining_time":0.6996199579},
{"learn":[3.529973872],"iteration":701,"passed_time":1.642281983,"remaining_time":0.6971510414},
{"learn":[3.527325183],"iteration":702,"passed_time":1.643987839,"remaining_time":0.6945439377},
{"learn":[3.527200815],"iteration":703,"passed_time":1.645818407,"remaining_time":0.6919918304},
{"learn":[3.523459911],"iteration":704,"passed_time":1.647680407,"remaining_time":0.6894549222},
{"learn":[3.522729934],"iteration":705,"passed_time":1.65017993,"remaining_time":0.6871854099},
{"learn":[3.522260582],"iteration":706,"passed_time":1.652296261,"remaining_time":0.6847564421},
{"learn":[3.518641591],"iteration":707,"passed_time":1.654044703,"remaining_time":0.6821766287},
{"learn":[3.516856405],"iteration":708,"passed_time":1.655714387,"remaining_time":0.6795668359},
{"learn":[3.515083413],"iteration":709,"passed_time":1.657567327,"remaining_time":0.6770345419},
{"learn":[3.514671214],"iteration":710,"passed_time":1.659322628,"remaining_time":0.6744644718},
{"learn":[3.512617621],"iteration":711,"passed_time":1.661233021,"remaining_time":0.6719594241},
{"learn":[3.510747971],"iteration":712,"passed_time":1.663319213,"remaining_time":0.6695268079},
{"learn":[3.508149266],"iteration":713,"passed_time":1.665569848,"remaining_time":0.6671610316},
{"learn":[3.504557165],"iteration":714,"passed_time":1.667467411,"remaining_time":0.6646548421},
{"learn":[3.501367208],"iteration":715,"passed_time":1.669079512,"remaining_time":0.6620371249},
{"learn":[3.497593362],"iteration":716,"passed_time":1.670742757,"remaining_time":0.6594423991},
{"learn":[3.496291169],"iteration":717,"passed_time":1.673258949,"remaining_time":0.6571852698},
{"learn":[3.49330374],"iteration":718,"passed_time":1.67535853,"remaining_time":0.6547645993},
{"learn":[3.490044385],"iteration":719,"passed_time":1.677224029,"remaining_time":0.652253789},
{"learn":[3.488891789],"iteration":720,"passed_time":1.679623664,"remaining_time":0.6499514596},
{"learn":[3.486869081],"iteration":721,"passed_time":1.6819047,"remaining_time":0.6476031946},
{"learn":[3.486303638],"iteration":722,"passed_time":1.684059033,"remaining_time":0.6452065729},
{"learn":[3.486035862],"iteration":723,"passed_time":1.685721604,"remaining_time":0.6426231528},
{"learn":[3.482668951],"iteration":724,"passed_time":1.687450398,"remaining_time":0.6400673922},
{"learn":[3.47820549],"iteration":725,"passed_time":1.688929827,"remaining_time":0.637419797},
{"learn":[3.474392283],"iteration":726,"passed_time":1.690946216,"remaining_time":0.6349770521},
{"learn":[3.472268163],"iteration":727,"passed_time":1.692824467,"remaining_time":0.6324838667},
{"learn":[3.471209164],"iteration":728,"passed_time":1.694883104,"remaining_time":0.6300594256},
{"learn":[3.470049971],"iteration":729,"passed_time":1.696797702,"remaining_time":0.6275827116},
{"learn":[3.469078654],"iteration":730,"passed_time":1.698502016,"remaining_time":0.6250301535},
{"learn":[3.468643292],"iteration":731,"passed_time":1.700057425,"remaining_time":0.6224253962},
{"learn":[3.468134848],"iteration":732,"passed_time":1.701662059,"remaining_time":0.6198414323},
{"learn":[3.467820182],"iteration":733,"passed_time":1.703173143,"remaining_time":0.6172262343},
{"learn":[3.465776156],"iteration":734,"passed_time":1.705179926,"remaining_time":0.6147927625},
{"learn":[3.463037608],"iteration":735,"passed_time":1.70742495,"remaining_time":0.612445906},
{"learn":[3.45965637],"iteration":736,"passed_time":1.709465813,"remaining_time":0.6100264707},
{"learn":[3.457275091],"iteration":737,"passed_time":1.711611478,"remaining_time":0.6076452671},
{"learn":[3.455522955],"iteration":738,"passed_time":1.713472866,"remaining_time":0.6051643004},
{"learn":[3.451270508],"iteration":739,"passed_time":1.715198973,"remaining_time":0.6026374771},
{"learn":[3.450978947],"iteration":740,"passed_time":1.7167996,"remaining_time":0.6000689559},
{"learn":[3.450608492],"iteration":741,"passed_time":1.718264463,"remaining_time":0.5974558376},
{"learn":[3.448122004],"iteration":742,"passed_time":1.72009177,"remaining_time":0.5949711777},
{"learn":[3.445646714],"iteration":743,"passed_time":1.722679694,"remaining_time":0.5927500023},
{"learn":[3.44411263],"iteration":744,"passed_time":1.724469129,"remaining_time":0.590254534},
{"learn":[3.443264164],"iteration":745,"passed_time":1.726345265,"remaining_time":0.5877904789},
{"learn":[3.439521363],"iteration":746,"passed_time":1.728220045,"remaining_time":0.5853275385},
{"learn":[3.436809225],"iteration":747,"passed_time":1.729990792,"remaining_time":0.5828311226},
{"learn":[3.435509465],"iteration":748,"passed_time":1.731716733,"remaining_time":0.5803216289},
{"learn":[3.434450277],"iteration":749,"passed_time":1.733449802,"remaining_time":0.5778166006},
{"learn":[3.431786753],"iteration":750,"passed_time":1.735320147,"remaining_time":0.5753591434},
{"learn":[3.430150302],"iteration":751,"passed_time":1.737224539,"remaining_time":0.5729144757},
{"learn":[3.42696281],"iteration":752,"passed_time":1.739023639,"remaining_time":0.5704367049},
{"learn":[3.426870334],"iteration":753,"passed_time":1.740614559,"remaining_time":0.5678928135},
{"learn":[3.425200309],"iteration":754,"passed_time":1.742595691,"remaining_time":0.5654780719},
{"learn":[3.423383783],"iteration":755,"passed_time":1.744323645,"remaining_time":0.5629827638},
{"learn":[3.422752979],"iteration":756,"passed_time":1.74580412,"remaining_time":0.5604100412},
{"learn":[3.420845924],"iteration":757,"passed_time":1.748073411,"remaining_time":0.5580920388},
{"learn":[3.418917862],"iteration":758,"passed_time":1.75022423,"remaining_time":0.5557365472},
{"learn":[3.417095735],"iteration":759,"passed_time":1.752238881,"remaining_time":0.5533385939},
{"learn":[3.414391848],"iteration":760,"passed_time":1.754021591,"remaining_time":0.5508688045},
{"learn":[3.41426711],"iteration":761,"passed_time":1.756007512,"remaining_time":0.5484642885},
{"learn":[3.411976013],"iteration":762,"passed_time":1.757717329,"remaining_time":0.5459751074},
{"learn":[3.408614844],"iteration":763,"passed_time":1.75946743,"remaining_time":0.5435004102},
{"learn":[3.407906721],"iteration":764,"passed_time":1.761048154,"remaining_time":0.5409755769},
{"learn":[3.407494015],"iteration":765,"passed_time":1.762685155,"remaining_time":0.5384703998},
{"learn":[3.406287128],"iteration":766,"passed_time":1.764490328,"remaining_time":0.5360185744},
{"learn":[3.404600442],"iteration":767,"passed_time":1.76643111,"remaining_time":0.5336093978},
{"learn":[3.404012662],"iteration":768,"passed_time":1.7682819,"remaining_time":0.5311744069},
{"learn":[3.400398762],"iteration":769,"passed_time":1.770299506,"remaining_time":0.5287907614},
{"learn":[3.399737714],"iteration":770,"passed_time":1.772069525,"remaining_time":0.5263345281},
{"learn":[3.399185251],"iteration":771,"passed_time":1.773749427,"remaining_time":0.5238534577},
{"learn":[3.397245411],"iteration":772,"passed_time":1.775531779,"remaining_time":0.5214045456},
{"learn":[3.396229831],"iteration":773,"passed_time":1.777059663,"remaining_time":0.5188830541},
{"learn":[3.394002836],"iteration":774,"passed_time":1.778931621,"remaining_time":0.516464019},
{"learn":[3.389617243],"iteration":775,"passed_time":1.780924529,"remaining_time":0.5140813073},
{"learn":[3.385426488],"iteration":776,"passed_time":1.783217538,"remaining_time":0.5117857283},
{"learn":[3.385072258],"iteration":777,"passed_time":1.785041871,"remaining_time":0.5093564207},
{"learn":[3.383842366],"iteration":778,"passed_time":1.786959271,"remaining_time":0.5069550692},
{"learn":[3.380110746],"iteration":779,"passed_time":1.789213868,"remaining_time":0.5046500654},
{"learn":[3.378595218],"iteration":780,"passed_time":1.791087264,"remaining_time":0.502238298},
{"learn":[3.377371219],"iteration":781,"passed_time":1.792941646,"remaining_time":0.4998226073},
{"learn":[3.375814782],"iteration":782,"passed_time":1.795130907,"remaining_time":0.4975011581},
{"learn":[3.374195887],"iteration":783,"passed_time":1.797186158,"remaining_time":0.4951431253},
{"learn":[3.373704309],"iteration":784,"passed_time":1.799005546,"remaining_time":0.4927212641},
{"learn":[3.372971757],"iteration":785,"passed_time":1.800719671,"remaining_time":0.4902722769},
{"learn":[3.371565136],"iteration":786,"passed_time":1.802369103,"remaining_time":0.4878076479},
{"learn":[3.3700309],"iteration":787,"passed_time":1.803977292,"remaining_time":0.4853339923},
{"learn":[3.368186663],"iteration":788,"passed_time":1.805685209,"remaining_time":0.4828892005},
{"learn":[3.366710398],"iteration":789,"passed_time":1.807333988,"remaining_time":0.4804305537},
{"learn":[3.364598042],"iteration":790,"passed_time":1.809024282,"remaining_time":0.477984924},
{"learn":[3.36348442],"iteration":791,"passed_time":1.811069333,"remaining_time":0.4756343702},
{"learn":[3.362001759],"iteration":792,"passed_time":1.812668503,"remaining_time":0.4731681968},
{"learn":[3.361580401],"iteration":793,"passed_time":1.81445987,"remaining_time":0.4707540719},
{"learn":[3.359543675],"iteration":794,"passed_time":1.816629767,"remaining_time":0.4684391222},
{"learn":[3.35766119],"iteration":795,"passed_time":1.818577385,"remaining_time":0.466067571},
{"learn":[3.354592969],"iteration":796,"passed_time":1.820215118,"remaining_time":0.4636181542},
{"learn":[3.350985986],"iteration":797,"passed_time":1.821782157,"remaining_time":0.4611528768},
{"learn":[3.349589624],"iteration":798,"passed_time":1.823591578,"remaining_time":0.4587508225},
{"learn":[3.349110856],"iteration":799,"passed_time":1.825964885,"remaining_time":0.4564912213},
{"learn":[3.345315441],"iteration":800,"passed_time":1.828305884,"remaining_time":0.4542233095},
{"learn":[3.34397474],"iteration":801,"passed_time":1.830267901,"remaining_time":0.4518616513},
{"learn":[3.343800902],"iteration":802,"passed_time":1.832123118,"remaining_time":0.4494747874},
{"learn":[3.342329465],"iteration":803,"passed_time":1.83432175,"remaining_time":0.4471729639},
{"learn":[3.34220347],"iteration":804,"passed_time":1.836016401,"remaining_time":0.4447493145},
{"learn":[3.341279219],"iteration":805,"passed_time":1.837796375,"remaining_time":0.4423480109},
{"learn":[3.337329521],"iteration":806,"passed_time":1.839407044,"remaining_time":0.4399077565},
{"learn":[3.336708453],"iteration":807,"passed_time":1.84167758,"remaining_time":0.4376263557},
{"learn":[3.333252703],"iteration":808,"passed_time":1.843448138,"remaining_time":0.43522694},
{"learn":[3.332186769],"iteration":809,"passed_time":1.845304201,"remaining_time":0.4328491335},
{"learn":[3.330594851],"iteration":810,"passed_time":1.84710132,"remaining_time":0.4304588774},
{"learn":[3.327867442],"iteration":811,"passed_time":1.848888731,"remaining_time":0.4280678343},
{"learn":[3.327563111],"iteration":812,"passed_time":1.850549856,"remaining_time":0.425649229},
{"learn":[3.326308994],"iteration":813,"passed_time":1.852066863,"remaining_time":0.4231995535},
{"learn":[3.326249879],"iteration":814,"passed_time":1.853910574,"remaining_time":0.4208263267},
{"learn":[3.322336238],"iteration":815,"passed_time":1.856442131,"remaining_time":0.4186095002},
{"learn":[3.320491154],"iteration":816,"passed_time":1.858385181,"remaining_time":0.4162600834},
{"learn":[3.320434271],"iteration":817,"passed_time":1.860036785,"remaining_time":0.4138468152},
{"learn":[3.319609638],"iteration":818,"passed_time":1.862006771,"remaining_time":0.41150577},
{"learn":[3.316182682],"iteration":819,"passed_time":1.864108024,"remaining_time":0.4091944442},
{"learn":[3.313126612],"iteration":820,"passed_time":1.865926711,"remaining_time":0.4068220234},
{"learn":[3.311222803],"iteration":821,"passed_time":1.867701393,"remaining_time":0.4044414209},
{"learn":[3.309627335],"iteration":822,"passed_time":1.869885042,"remaining_time":0.402150246},
{"learn":[3.307974895],"iteration":823,"passed_time":1.872509397,"remaining_time":0.3999534635},
{"learn":[3.307321505],"iteration":824,"passed_time":1.874480664,"remaining_time":0.3976171106},
{"learn":[3.306759087],"iteration":825,"passed_time":1.876603212,"remaining_time":0.3953135096},
{"learn":[3.30484037],"iteration":826,"passed_time":1.878704789,"remaining_time":0.3930059595},
{"learn":[3.30201994],"iteration":827,"passed_time":1.880438584,"remaining_time":0.3906225077},
{"learn":[3.299302297],"iteration":828,"passed_time":1.882322628,"remaining_time":0.3882716157},
{"learn":[3.298132671],"iteration":829,"passed_time":1.884562384,"remaining_time":0.3859947052},
{"learn":[3.296976183],"iteration":830,"passed_time":1.887069059,"remaining_time":0.3837721673},
{"learn":[3.293144745],"iteration":831,"passed_time":1.888966155,"remaining_time":0.3814258583},
{"learn":[3.290284404],"iteration":832,"passed_time":1.891089418,"remaining_time":0.3791259697},
{"learn":[3.288285745],"iteration":833,"passed_time":1.892880974,"remaining_time":0.3767604817},
{"learn":[3.286662667],"iteration":834,"passed_time":1.894759906,"remaining_time":0.374413634},
{"learn":[3.285692682],"iteration":835,"passed_time":1.896489461,"remaining_time":0.3720386024},
{"learn":[3.284565611],"iteration":836,"passed_time":1.898278052,"remaining_time":0.36967661},
{"learn":[3.283897383],"iteration":837,"passed_time":1.901433877,"remaining_time":0.367580296},
{"learn":[3.280712855],"iteration":838,"passed_time":1.903956716,"remaining_time":0.3653599896},
{"learn":[3.280468341],"iteration":839,"passed_time":1.905946269,"remaining_time":0.3630373846},
{"learn":[3.277814895],"iteration":840,"passed_time":1.907847657,"remaining_time":0.360698903},
{"learn":[3.276316385],"iteration":841,"passed_time":1.909661231,"remaining_time":0.3583449816},
{"learn":[3.27557063],"iteration":842,"passed_time":1.911780997,"remaining_time":0.3560493673},
{"learn":[3.27499628],"iteration":843,"passed_time":1.913660404,"remaining_time":0.3537097429},
{"learn":[3.273569958],"iteration":844,"passed_time":1.915811407,"remaining_time":0.3514210272},
{"learn":[3.269665595],"iteration":845,"passed_time":1.917849829,"remaining_time":0.3491121439},
{"learn":[3.267984685],"iteration":846,"passed_time":1.919731447,"remaining_time":0.3467755742},
{"learn":[3.267702508],"iteration":847,"passed_time":1.921566979,"remaining_time":0.344431817},
{"learn":[3.266671924],"iteration":848,"passed_time":1.923686804,"remaining_time":0.3421398202},
{"learn":[3.265359825],"iteration":849,"passed_time":1.925665405,"remaining_time":0.3398233068},
{"learn":[3.2618983],"iteration":850,"passed_time":1.927480329,"remaining_time":0.3374789296},
{"learn":[3.260456253],"iteration":851,"passed_time":1.929698418,"remaining_time":0.3352058285},
{"learn":[3.258389147],"iteration":852,"passed_time":1.931786604,"remaining_time":0.3329104699},
{"learn":[3.258108469],"iteration":853,"passed_time":1.935496791,"remaining_time":0.3308928941},
{"learn":[3.256424936],"iteration":854,"passed_time":1.937900766,"remaining_time":0.3286498376},
{"learn":[3.254817983],"iteration":855,"passed_time":1.940023496,"remaining_time":0.3263590928},
{"learn":[3.253898449],"iteration":856,"passed_time":1.942204359,"remaining_time":0.3240784403},
{"learn":[3.253023652],"iteration":857,"passed_time":1.945254975,"remaining_time":0.3219419656},
{"learn":[3.252845542],"iteration":858,"passed_time":1.947312463,"remaining_time":0.3196403461},
{"learn":[3.252316026],"iteration":859,"passed_time":1.949374986,"remaining_time":0.317340114},
{"learn":[3.24975301],"iteration":860,"passed_time":1.951651339,"remaining_time":0.3150749549},
{"learn":[3.249151075],"iteration":861,"passed_time":1.953825725,"remaining_time":0.3127934455},
{"learn":[3.246257135],"iteration":862,"passed_time":1.955638584,"remaining_time":0.3104547926},
{"learn":[3.243826471],"iteration":863,"passed_time":1.957736031,"remaining_time":0.308162153},
{"learn":[3.243190653],"iteration":864,"passed_time":1.9605349,"remaining_time":0.3059794353},
{"learn":[3.24008797],"iteration":865,"passed_time":1.962722819,"remaining_time":0.3037007595},
{"learn":[3.240036811],"iteration":866,"passed_time":1.964842634,"remaining_time":0.3014118458},
{"learn":[3.238676314],"iteration":867,"passed_time":1.967615818,"remaining_time":0.299222682},
{"learn":[3.237848782],"iteration":868,"passed_time":1.969841911,"remaining_time":0.2969497012},
{"learn":[3.236405498],"iteration":869,"passed_time":1.971762077,"remaining_time":0.2946311149},
{"learn":[3.233378068],"iteration":870,"passed_time":1.975477517,"remaining_time":0.2925793338},
{"learn":[3.233169169],"iteration":871,"passed_time":1.977864332,"remaining_time":0.2903287093},
{"learn":[3.232434885],"iteration":872,"passed_time":1.98027688,"remaining_time":0.2880815163},
{"learn":[3.229978115],"iteration":873,"passed_time":1.982297267,"remaining_time":0.2857774093},
{"learn":[3.229648848],"iteration":874,"passed_time":1.984037823,"remaining_time":0.2834339747},
{"learn":[3.227208761],"iteration":875,"passed_time":1.985802033,"remaining_time":0.2810952649},
{"learn":[3.226258869],"iteration":876,"passed_time":1.987529123,"remaining_time":0.2787526592},
{"learn":[3.225331995],"iteration":877,"passed_time":1.990413087,"remaining_time":0.2765722057},
{"learn":[3.221968268],"iteration":878,"passed_time":1.992662283,"remaining_time":0.2743027716},
{"learn":[3.221166317],"iteration":879,"passed_time":1.994567784,"remaining_time":0.271986516},
{"learn":[3.220047503],"iteration":880,"passed_time":1.99658557,"remaining_time":0.2696863596},
{"learn":[3.21982781],"iteration":881,"passed_time":1.998531538,"remaining_time":0.2673772353},
{"learn":[3.216693405],"iteration":882,"passed_time":2.000436537,"remaining_time":0.2650635049},
{"learn":[3.214798761],"iteration":883,"passed_time":2.002649462,"remaining_time":0.2627911058},
{"learn":[3.214395085],"iteration":884,"passed_time":2.00579734,"remaining_time":0.2606403323},
{"learn":[3.213470696],"iteration":885,"passed_time":2.008289309,"remaining_time":0.2584029134},
{"learn":[3.211595017],"iteration":886,"passed_time":2.010186962,"remaining_time":0.2560892071},
{"learn":[3.210965255],"iteration":887,"passed_time":2.012037507,"remaining_time":0.2537704963},
{"learn":[3.209413583],"iteration":888,"passed_time":2.014004518,"remaining_time":0.2514673808},
{"learn":[3.208331683],"iteration":889,"passed_time":2.015976923,"remaining_time":0.2491656871},
{"learn":[3.207110711],"iteration":890,"passed_time":2.017992013,"remaining_time":0.2468699545},
{"learn":[3.204519413],"iteration":891,"passed_time":2.02117299,"remaining_time":0.2447160122},
{"learn":[3.201421296],"iteration":892,"passed_time":2.023331415,"remaining_time":0.2424372469},
{"learn":[3.200691259],"iteration":893,"passed_time":2.025386454,"remaining_time":0.2401464923},
{"learn":[3.200485067],"iteration":894,"passed_time":2.027396597,"remaining_time":0.2378509975},
{"learn":[3.197467568],"iteration":895,"passed_time":2.030013168,"remaining_time":0.2356265285},
{"learn":[3.195838544],"iteration":896,"passed_time":2.031870027,"remaining_time":0.2333139496},
{"learn":[3.195671746],"iteration":897,"passed_time":2.03418779,"remaining_time":0.2310547379},
{"learn":[3.194213094],"iteration":898,"passed_time":2.037028907,"remaining_time":0.2288541931},
{"learn":[3.192884691],"iteration":899,"passed_time":2.039041492,"remaining_time":0.2265601658},
{"learn":[3.188364239],"iteration":900,"passed_time":2.040993864,"remaining_time":0.2242601471},
{"learn":[3.185219478],"iteration":901,"passed_time":2.043071053,"remaining_time":0.2219744603},
{"learn":[3.184120387],"iteration":902,"passed_time":2.045272407,"remaining_time":0.2197025731},
{"learn":[3.183725321],"iteration":903,"passed_time":2.047233832,"remaining_time":0.2174053627},
{"learn":[3.181264554],"iteration":904,"passed_time":2.048916537,"remaining_time":0.2150796365},
{"learn":[3.180741589],"iteration":905,"passed_time":2.051357814,"remaining_time":0.2128340337},
{"learn":[3.179782639],"iteration":906,"passed_time":2.053776865,"remaining_time":0.2105857205},
{"learn":[3.176377564],"iteration":907,"passed_time":2.055703081,"remaining_time":0.2082870963},
{"learn":[3.174078182],"iteration":908,"passed_time":2.057383584,"remaining_time":0.2059646932},
{"learn":[3.171242379],"iteration":909,"passed_time":2.059097253,"remaining_time":0.203646981},
{"learn":[3.170421012],"iteration":910,"passed_time":2.060875749,"remaining_time":0.2013369283},
{"learn":[3.170087224],"iteration":911,"passed_time":2.062622113,"remaining_time":0.1990249407},
{"learn":[3.167303059],"iteration":912,"passed_time":2.064916643,"remaining_time":0.1967664271},
{"learn":[3.16705966],"iteration":913,"passed_time":2.066870361,"remaining_time":0.194475767},
{"learn":[3.165667683],"iteration":914,"passed_time":2.068608853,"remaining_time":0.1921658497},
{"learn":[3.164689733],"iteration":915,"passed_time":2.07071616,"remaining_time":0.1898910016},
{"learn":[3.163311455],"iteration":916,"passed_time":2.072521975,"remaining_time":0.18758923},
{"learn":[3.159425016],"iteration":917,"passed_time":2.074536747,"remaining_time":0.185307204},
{"learn":[3.159327058],"iteration":918,"passed_time":2.076182508,"remaining_time":0.1829932352},
{"learn":[3.15819426],"iteration":919,"passed_time":2.077905969,"remaining_time":0.1806874756},
{"learn":[3.157086603],"iteration":920,"passed_time":2.08029006,"remaining_time":0.1784396468},
{"learn":[3.153354154],"iteration":921,"passed_time":2.082671548,"remaining_time":0.1761913023},
{"learn":[3.153261317],"iteration":922,"passed_time":2.084678838,"remaining_time":0.1739114524},
{"learn":[3.153168454],"iteration":923,"passed_time":2.086609412,"remaining_time":0.1716258824},
{"learn":[3.152080399],"iteration":924,"passed_time":2.089774311,"remaining_time":0.1694411603},
{"learn":[3.151635144],"iteration":925,"passed_time":2.092070718,"remaining_time":0.167184917},
{"learn":[3.147762655],"iteration":926,"passed_time":2.094225514,"remaining_time":0.1649174353},
{"learn":[3.147172317],"iteration":927,"passed_time":2.096584269,"remaining_time":0.1626660209},
{"learn":[3.146254125],"iteration":928,"passed_time":2.098567047,"remaining_time":0.1603856408},
{"learn":[3.144869828],"iteration":929,"passed_time":2.100669222,"remaining_time":0.1581148877},
{"learn":[3.143466218],"iteration":930,"passed_time":2.102884418,"remaining_time":0.1558528731},
{"learn":[3.141919643],"iteration":931,"passed_time":2.105156829,"remaining_time":0.1535951334},
{"learn":[3.141054135],"iteration":932,"passed_time":2.107383652,"remaining_time":0.1513340886},
{"learn":[3.139390417],"iteration":933,"passed_time":2.1095353,"remaining_time":0.1490678049},
{"learn":[3.139025283],"iteration":934,"passed_time":2.111479875,"remaining_time":0.146787371},
{"learn":[3.137824183],"iteration":935,"passed_time":2.113231088,"remaining_time":0.1444944333},
{"learn":[3.135620453],"iteration":936,"passed_time":2.115172412,"remaining_time":0.1422154343},
{"learn":[3.13443178],"iteration":937,"passed_time":2.117038021,"remaining_time":0.1399321506},
{"learn":[3.132765713],"iteration":938,"passed_time":2.119706092,"remaining_time":0.1377018867},
{"learn":[3.131434124],"iteration":939,"passed_time":2.12227765,"remaining_time":0.1354645308},
{"learn":[3.128384262],"iteration":940,"passed_time":2.124342569,"remaining_time":0.1331946988},
{"learn":[3.128120455],"iteration":941,"passed_time":2.126807557,"remaining_time":0.1309499345},
{"learn":[3.126314615],"iteration":942,"passed_time":2.129648507,"remaining_time":0.1287274283},
{"learn":[3.125409666],"iteration":943,"passed_time":2.131680993,"remaining_time":0.1264556521},
{"learn":[3.123072589],"iteration":944,"passed_time":2.133544531,"remaining_time":0.1241745494},
{"learn":[3.122921099],"iteration":945,"passed_time":2.136805901,"remaining_time":0.1219741212},
{"learn":[3.122182662],"iteration":946,"passed_time":2.138803146,"remaining_time":0.119700704},
{"learn":[3.120040951],"iteration":947,"passed_time":2.140879811,"remaining_time":0.1174322259},
{"learn":[3.118767799],"iteration":948,"passed_time":2.142937555,"remaining_time":0.1151631352},
{"learn":[3.118203218],"iteration":949,"passed_time":2.144733244,"remaining_time":0.1128806971},
{"learn":[3.116343362],"iteration":950,"passed_time":2.146441487,"remaining_time":0.1105947769},
{"learn":[3.11480829],"iteration":951,"passed_time":2.148567341,"remaining_time":0.1083311264},
{"learn":[3.112607903],"iteration":952,"passed_time":2.151454988,"remaining_time":0.1061053352},
{"learn":[3.111661241],"iteration":953,"passed_time":2.153557929,"remaining_time":0.1038403195},
{"learn":[3.110249676],"iteration":954,"passed_time":2.155907556,"remaining_time":0.1015872671},
{"learn":[3.107333579],"iteration":955,"passed_time":2.157814099,"remaining_time":0.09931361963},
{"learn":[3.107149851],"iteration":956,"passed_time":2.159458107,"remaining_time":0.09702894317},
{"learn":[3.106867336],"iteration":957,"passed_time":2.161273693,"remaining_time":0.09475312642},
{"learn":[3.10364681],"iteration":958,"passed_time":2.163336801,"remaining_time":0.09248885175},
{"learn":[3.102703811],"iteration":959,"passed_time":2.165592709,"remaining_time":0.09023302956},
{"learn":[3.101469264],"iteration":960,"passed_time":2.167348717,"remaining_time":0.08795691985},
{"learn":[3.09863569],"iteration":961,"passed_time":2.169687018,"remaining_time":0.08570489262},
{"learn":[3.09645939],"iteration":962,"passed_time":2.17148571,"remaining_time":0.08343195357},
{"learn":[3.096240186],"iteration":963,"passed_time":2.17346238,"remaining_time":0.08116664488},
{"learn":[3.094838828],"iteration":964,"passed_time":2.175250474,"remaining_time":0.07889509493},
{"learn":[3.094176802],"iteration":965,"passed_time":2.17703966,"remaining_time":0.07662458432},
{"learn":[3.093182279],"iteration":966,"passed_time":2.17990176,"remaining_time":0.07439168364},
{"learn":[3.090150687],"iteration":967,"passed_time":2.182375709,"remaining_time":0.07214465153},
{"learn":[3.088612829],"iteration":968,"passed_time":2.184492874,"remaining_time":0.06988573693},
{"learn":[3.087153684],"iteration":969,"passed_time":2.186592464,"remaining_time":0.06762657104},
{"learn":[3.085866843],"iteration":970,"passed_time":2.189140704,"remaining_time":0.06538113329},
{"learn":[3.082669094],"iteration":971,"passed_time":2.191041818,"remaining_time":0.06311643096},
{"learn":[3.081047548],"iteration":972,"passed_time":2.192762834,"remaining_time":0.06084747844},
{"learn":[3.079684322],"iteration":973,"passed_time":2.195238593,"remaining_time":0.05859979817},
{"learn":[3.07613431],"iteration":974,"passed_time":2.197246189,"remaining_time":0.05633964587},
{"learn":[3.074005935],"iteration":975,"passed_time":2.19928924,"remaining_time":0.05408088296},
{"learn":[3.072988853],"iteration":976,"passed_time":2.201055282,"remaining_time":0.05181604041},
{"learn":[3.072344268],"iteration":977,"passed_time":2.202721008,"remaining_time":0.04954996133},
{"learn":[3.070654438],"iteration":978,"passed_time":2.205210586,"remaining_time":0.04730278071},
{"learn":[3.069724506],"iteration":979,"passed_time":2.207019594,"remaining_time":0.04504121621},
{"learn":[3.067763166],"iteration":980,"passed_time":2.209191108,"remaining_time":0.04278759537},
{"learn":[3.066737893],"iteration":981,"passed_time":2.211913519,"remaining_time":0.04054423965},
{"learn":[3.065248174],"iteration":982,"passed_time":2.213965578,"remaining_time":0.0382883162},
{"learn":[3.063186837],"iteration":983,"passed_time":2.215770613,"remaining_time":0.03602879046},
{"learn":[3.062880371],"iteration":984,"passed_time":2.217420877,"remaining_time":0.03376783061},
{"learn":[3.061288645],"iteration":985,"passed_time":2.219024853,"remaining_time":0.03150745227},
{"learn":[3.059970575],"iteration":986,"passed_time":2.220698836,"remaining_time":0.02924932611},
{"learn":[3.059576341],"iteration":987,"passed_time":2.22249595,"remaining_time":0.02699387794},
{"learn":[3.058175919],"iteration":988,"passed_time":2.224683648,"remaining_time":0.02474370084},
{"learn":[3.056830702],"iteration":989,"passed_time":2.226872092,"remaining_time":0.0224936575},
{"learn":[3.056336579],"iteration":990,"passed_time":2.228618568,"remaining_time":0.02023972464},
{"learn":[3.055810414],"iteration":991,"passed_time":2.230163595,"remaining_time":0.01798519029},
{"learn":[3.055476518],"iteration":992,"passed_time":2.23164824,"remaining_time":0.01573165929},
{"learn":[3.053331734],"iteration":993,"passed_time":2.233354554,"remaining_time":0.0134810134},
{"learn":[3.050890374],"iteration":994,"passed_time":2.23511303,"remaining_time":0.01123172377},
{"learn":[3.04972623],"iteration":995,"passed_time":2.236686479,"remaining_time":0.008982676624},
{"learn":[3.047217327],"iteration":996,"passed_time":2.238332491,"remaining_time":0.006735203081},
{"learn":[3.047155483],"iteration":997,"passed_time":2.240351109,"remaining_time":0.004489681582},
{"learn":[3.04430671],"iteration":998,"passed_time":2.242151731,"remaining_time":0.002244396127},
{"learn":[3.042664195],"iteration":999,"passed_time":2.243764942,"remaining_time":0}
]}